{"Hubscop-1":{
 "execution_paths": "65", 
 "callstack": false, 
 "reentrancy": false, 
 "modulo": false, 
 "division": false, 
 "execution_time": "50.1071009636", 
 "signedness": false, 
 "evm_code_coverage": "78.2", 
 "underflow": "\n./0x001fc4a7f2f586596308091c7b296d4535a25a90_ext.sol:Hubscop:103:16\n_totalSupply  - balances[address(0)]\n^", 
 "time_dependency": false, 
 "assertion_failure": false, 
 "timeout": true, 
 "dead_code": [
  "DUP1 ", 
  "PUSH4 0xd05c78da ", 
  "EQ ", 
  "PUSH2 0x05b5 ", 
  "JUMPI ", 
  "DUP1 ", 
  "PUSH4 0xd4ee1d90 ", 
  "EQ ", 
  "PUSH2 0x05f5 ", 
  "JUMPI ", 
  "DUP1 ", 
  "PUSH4 0xdc39d06d ", 
  "EQ ", 
  "PUSH2 0x064a ", 
  "JUMPI ", 
  "DUP1 ", 
  "PUSH4 0xdd62ed3e ", 
  "EQ ", 
  "PUSH2 0x06a4 ", 
  "JUMPI ", 
  "DUP1 ", 
  "PUSH4 0xe6cb9013 ", 
  "EQ ", 
  "PUSH2 0x0710 ", 
  "JUMPI ", 
  "DUP1 ", 
  "PUSH4 0xf2fde38b ", 
  "EQ ", 
  "PUSH2 0x0750 ", 
  "JUMPI ", 
  "JUMPDEST ", 
  "PUSH1 0x00 ", 
  "DUP2 ", 
  "DUP4 ", 
  "MUL ", 
  "SWAP1 ", 
  "POP ", 
  "PUSH1 0x00 ", 
  "DUP4 ", 
  "EQ ", 
  "DUP1 ", 
  "PUSH2 0x12eb ", 
  "JUMPI ", 
  "POP ", 
  "DUP2 ", 
  "DUP4 ", 
  "DUP3 ", 
  "DUP2 ", 
  "ISZERO ", 
  "ISZERO ", 
  "PUSH2 0x12e8 ", 
  "JUMPI ", 
  "ASSERTFAIL ", 
  "JUMPDEST ", 
  "DIV ", 
  "EQ ", 
  "JUMPDEST ", 
  "ISZERO ", 
  "ISZERO ", 
  "PUSH2 0x12f6 ", 
  "JUMPI ", 
  "PUSH1 0x00 ", 
  "DUP1 ", 
  "REVERT ", 
  "JUMPDEST ", 
  "SWAP3 ", 
  "SWAP2 ", 
  "POP ", 
  "POP ", 
  "JUMP ", 
  "JUMPDEST ", 
  "PUSH1 0x01 ", 
  "PUSH1 0x00 ", 
  "SWAP1 ", 
  "SLOAD ", 
  "SWAP1 ", 
  "PUSH2 0x0100 ", 
  "EXP ", 
  "SWAP1 ", 
  "DIV ", 
  "PUSH20 0xffffffffffffffffffffffffffffffffffffffff ", 
  "AND ", 
  "DUP2 ", 
  "JUMP ", 
  "JUMPDEST ", 
  "PUSH1 0x00 ", 
  "DUP1 ", 
  "PUSH1 0x00 ", 
  "SWAP1 ", 
  "SLOAD ", 
  "SWAP1 ", 
  "PUSH2 0x0100 ", 
  "EXP ", 
  "SWAP1 ", 
  "DIV ", 
  "PUSH20 0xffffffffffffffffffffffffffffffffffffffff ", 
  "AND ", 
  "PUSH20 0xffffffffffffffffffffffffffffffffffffffff ", 
  "AND ", 
  "CALLER ", 
  "PUSH20 0xffffffffffffffffffffffffffffffffffffffff ", 
  "AND ", 
  "EQ ", 
  "ISZERO ", 
  "ISZERO ", 
  "PUSH2 0x137f ", 
  "JUMPI ", 
  "PUSH1 0x00 ", 
  "DUP1 ", 
  "REVERT ", 
  "JUMPDEST ", 
  "DUP3 ", 
  "PUSH20 0xffffffffffffffffffffffffffffffffffffffff ", 
  "AND ", 
  "PUSH4 0xa9059cbb ", 
  "PUSH1 0x00 ", 
  "DUP1 ", 
  "SWAP1 ", 
  "SLOAD ", 
  "SWAP1 ", 
  "PUSH2 0x0100 ", 
  "EXP ", 
  "SWAP1 ", 
  "DIV ", 
  "PUSH20 0xffffffffffffffffffffffffffffffffffffffff ", 
  "AND ", 
  "DUP5 ", 
  "PUSH1 0x00 ", 
  "PUSH1 0x40 ", 
  "MLOAD ", 
  "PUSH1 0x20 ", 
  "ADD ", 
  "MSTORE ", 
  "PUSH1 0x40 ", 
  "MLOAD ", 
  "DUP4 ", 
  "PUSH4 0xffffffff ", 
  "AND ", 
  "PUSH29 0x0100000000000000000000000000000000000000000000000000000000 ", 
  "MUL ", 
  "DUP2 ", 
  "MSTORE ", 
  "PUSH1 0x04 ", 
  "ADD ", 
  "DUP1 ", 
  "DUP4 ", 
  "PUSH20 0xffffffffffffffffffffffffffffffffffffffff ", 
  "AND ", 
  "PUSH20 0xffffffffffffffffffffffffffffffffffffffff ", 
  "AND ", 
  "DUP2 ", 
  "MSTORE ", 
  "PUSH1 0x20 ", 
  "ADD ", 
  "DUP3 ", 
  "DUP2 ", 
  "MSTORE ", 
  "PUSH1 0x20 ", 
  "ADD ", 
  "SWAP3 ", 
  "POP ", 
  "POP ", 
  "POP ", 
  "PUSH1 0x20 ", 
  "PUSH1 0x40 ", 
  "MLOAD ", 
  "DUP1 ", 
  "DUP4 ", 
  "SUB ", 
  "DUP2 ", 
  "PUSH1 0x00 ", 
  "DUP8 ", 
  "DUP1 ", 
  "EXTCODESIZE ", 
  "ISZERO ", 
  "ISZERO ", 
  "PUSH2 0x144b ", 
  "JUMPI ", 
  "PUSH1 0x00 ", 
  "DUP1 ", 
  "REVERT ", 
  "JUMPDEST ", 
  "PUSH2 0x02c6 ", 
  "GAS ", 
  "SUB ", 
  "CALL ", 
  "ISZERO ", 
  "ISZERO ", 
  "PUSH2 0x145c ", 
  "JUMPI ", 
  "PUSH1 0x00 ", 
  "DUP1 ", 
  "REVERT ", 
  "JUMPDEST ", 
  "POP ", 
  "POP ", 
  "POP ", 
  "PUSH1 0x40 ", 
  "MLOAD ", 
  "DUP1 ", 
  "MLOAD ", 
  "SWAP1 ", 
  "POP ", 
  "SWAP1 ", 
  "POP ", 
  "SWAP3 ", 
  "SWAP2 ", 
  "POP ", 
  "POP ", 
  "JUMP ", 
  "JUMPDEST ", 
  "PUSH1 0x00 ", 
  "PUSH1 0x07 ", 
  "PUSH1 0x00 ", 
  "DUP5 ", 
  "PUSH20 0xffffffffffffffffffffffffffffffffffffffff ", 
  "AND ", 
  "PUSH20 0xffffffffffffffffffffffffffffffffffffffff ", 
  "AND ", 
  "DUP2 ", 
  "MSTORE ", 
  "PUSH1 0x20 ", 
  "ADD ", 
  "SWAP1 ", 
  "DUP2 ", 
  "MSTORE ", 
  "PUSH1 0x20 ", 
  "ADD ", 
  "PUSH1 0x00 ", 
  "SHA3 ", 
  "PUSH1 0x00 ", 
  "DUP4 ", 
  "PUSH20 0xffffffffffffffffffffffffffffffffffffffff ", 
  "AND ", 
  "PUSH20 0xffffffffffffffffffffffffffffffffffffffff ", 
  "AND ", 
  "DUP2 ", 
  "MSTORE ", 
  "PUSH1 0x20 ", 
  "ADD ", 
  "SWAP1 ", 
  "DUP2 ", 
  "MSTORE ", 
  "PUSH1 0x20 ", 
  "ADD ", 
  "PUSH1 0x00 ", 
  "SHA3 ", 
  "SLOAD ", 
  "SWAP1 ", 
  "POP ", 
  "SWAP3 ", 
  "SWAP2 ", 
  "POP ", 
  "POP ", 
  "JUMP ", 
  "JUMPDEST ", 
  "PUSH1 0x00 ", 
  "DUP1 ", 
  "SWAP1 ", 
  "SLOAD ", 
  "SWAP1 ", 
  "PUSH2 0x0100 ", 
  "EXP ", 
  "SWAP1 ", 
  "DIV ", 
  "PUSH20 0xffffffffffffffffffffffffffffffffffffffff ", 
  "PUSH1 0x00 ", 
  "DUP1 ", 
  "REVERT ", 
  "AND ", 
  "PUSH20 0xffffffffffffffffffffffffffffffffffffffff ", 
  "AND ", 
  "CALLER ", 
  "PUSH20 0xffffffffffffffffffffffffffffffffffffffff ", 
  "AND ", 
  "EQ ", 
  "ISZERO ", 
  "ISZERO ", 
  "PUSH2 0x156c ", 
  "JUMPI ", 
  "PUSH1 0x00 ", 
  "DUP1 ", 
  "REVERT ", 
  "JUMPDEST ", 
  "DUP1 ", 
  "PUSH1 0x01 ", 
  "PUSH1 0x00 ", 
  "PUSH2 0x0100 ", 
  "EXP ", 
  "DUP2 ", 
  "SLOAD ", 
  "DUP2 ", 
  "PUSH20 0xffffffffffffffffffffffffffffffffffffffff ", 
  "MUL ", 
  "NOT ", 
  "AND ", 
  "SWAP1 ", 
  "DUP4 ", 
  "PUSH20 0xffffffffffffffffffffffffffffffffffffffff ", 
  "AND ", 
  "MUL ", 
  "OR ", 
  "SWAP1 ", 
  "SSTORE ", 
  "POP ", 
  "POP ", 
  "JUMP ", 
  "STOP ", 
  "JUMPDEST ", 
  "CALLVALUE ", 
  "ISZERO ", 
  "PUSH2 0x05c0 ", 
  "JUMPI ", 
  "PUSH1 0x00 ", 
  "DUP1 ", 
  "REVERT ", 
  "JUMPDEST ", 
  "PUSH2 0x05df ", 
  "PUSH1 0x04 ", 
  "DUP1 ", 
  "DUP1 ", 
  "CALLDATALOAD ", 
  "SWAP1 ", 
  "PUSH1 0x20 ", 
  "ADD ", 
  "SWAP1 ", 
  "SWAP2 ", 
  "SWAP1 ", 
  "DUP1 ", 
  "CALLDATALOAD ", 
  "SWAP1 ", 
  "PUSH1 0x20 ", 
  "ADD ", 
  "SWAP1 ", 
  "SWAP2 ", 
  "SWAP1 ", 
  "POP ", 
  "POP ", 
  "PUSH2 0x12cb ", 
  "JUMP ", 
  "JUMPDEST ", 
  "PUSH1 0x40 ", 
  "MLOAD ", 
  "DUP1 ", 
  "DUP3 ", 
  "DUP2 ", 
  "MSTORE ", 
  "PUSH1 0x20 ", 
  "ADD ", 
  "SWAP2 ", 
  "POP ", 
  "POP ", 
  "PUSH1 0x40 ", 
  "MLOAD ", 
  "DUP1 ", 
  "SWAP2 ", 
  "SUB ", 
  "SWAP1 ", 
  "RETURN ", 
  "JUMPDEST ", 
  "CALLVALUE ", 
  "ISZERO ", 
  "PUSH2 0x0600 ", 
  "JUMPI ", 
  "PUSH1 0x00 ", 
  "DUP1 ", 
  "REVERT ", 
  "JUMPDEST ", 
  "PUSH2 0x0608 ", 
  "PUSH2 0x12fc ", 
  "JUMP ", 
  "JUMPDEST ", 
  "PUSH1 0x40 ", 
  "MLOAD ", 
  "DUP1 ", 
  "DUP3 ", 
  "PUSH20 0xffffffffffffffffffffffffffffffffffffffff ", 
  "AND ", 
  "PUSH20 0xffffffffffffffffffffffffffffffffffffffff ", 
  "AND ", 
  "DUP2 ", 
  "MSTORE ", 
  "PUSH1 0x20 ", 
  "ADD ", 
  "SWAP2 ", 
  "POP ", 
  "POP ", 
  "PUSH1 0x40 ", 
  "MLOAD ", 
  "DUP1 ", 
  "SWAP2 ", 
  "SUB ", 
  "SWAP1 ", 
  "RETURN ", 
  "JUMPDEST ", 
  "CALLVALUE ", 
  "ISZERO ", 
  "PUSH2 0x0655 ", 
  "JUMPI ", 
  "PUSH1 0x00 ", 
  "DUP1 ", 
  "REVERT ", 
  "JUMPDEST ", 
  "PUSH2 0x068a ", 
  "PUSH1 0x04 ", 
  "DUP1 ", 
  "DUP1 ", 
  "CALLDATALOAD ", 
  "PUSH20 0xffffffffffffffffffffffffffffffffffffffff ", 
  "AND ", 
  "SWAP1 ", 
  "PUSH1 0x20 ", 
  "ADD ", 
  "SWAP1 ", 
  "SWAP2 ", 
  "SWAP1 ", 
  "DUP1 ", 
  "CALLDATALOAD ", 
  "SWAP1 ", 
  "PUSH1 0x20 ", 
  "ADD ", 
  "SWAP1 ", 
  "SWAP2 ", 
  "SWAP1 ", 
  "POP ", 
  "POP ", 
  "PUSH2 0x1322 ", 
  "JUMP ", 
  "JUMPDEST ", 
  "PUSH1 0x40 ", 
  "MLOAD ", 
  "DUP1 ", 
  "DUP3 ", 
  "ISZERO ", 
  "ISZERO ", 
  "ISZERO ", 
  "ISZERO ", 
  "DUP2 ", 
  "MSTORE ", 
  "PUSH1 0x20 ", 
  "ADD ", 
  "SWAP2 ", 
  "POP ", 
  "POP ", 
  "PUSH1 0x40 ", 
  "MLOAD ", 
  "DUP1 ", 
  "SWAP2 ", 
  "SUB ", 
  "SWAP1 ", 
  "RETURN ", 
  "JUMPDEST ", 
  "CALLVALUE ", 
  "ISZERO ", 
  "PUSH2 0x06af ", 
  "JUMPI ", 
  "PUSH1 0x00 ", 
  "DUP1 ", 
  "REVERT ", 
  "JUMPDEST ", 
  "PUSH2 0x06fa ", 
  "PUSH1 0x04 ", 
  "DUP1 ", 
  "DUP1 ", 
  "CALLDATALOAD ", 
  "PUSH20 0xffffffffffffffffffffffffffffffffffffffff ", 
  "AND ", 
  "SWAP1 ", 
  "PUSH1 0x20 ", 
  "ADD ", 
  "SWAP1 ", 
  "SWAP2 ", 
  "SWAP1 ", 
  "DUP1 ", 
  "CALLDATALOAD ", 
  "PUSH20 0xffffffffffffffffffffffffffffffffffffffff ", 
  "AND ", 
  "SWAP1 ", 
  "PUSH1 0x20 ", 
  "ADD ", 
  "SWAP1 ", 
  "SWAP2 ", 
  "SWAP1 ", 
  "POP ", 
  "POP ", 
  "PUSH2 0x146e ", 
  "JUMP ", 
  "JUMPDEST ", 
  "PUSH1 0x40 ", 
  "MLOAD ", 
  "DUP1 ", 
  "DUP3 ", 
  "DUP2 ", 
  "MSTORE ", 
  "PUSH1 0x20 ", 
  "ADD ", 
  "SWAP2 ", 
  "POP ", 
  "POP ", 
  "PUSH1 0x40 ", 
  "MLOAD ", 
  "DUP1 ", 
  "SWAP2 ", 
  "SUB ", 
  "SWAP1 ", 
  "RETURN ", 
  "JUMPDEST ", 
  "CALLVALUE ", 
  "ISZERO ", 
  "PUSH2 0x071b ", 
  "JUMPI ", 
  "PUSH1 0x00 ", 
  "DUP1 ", 
  "REVERT ", 
  "JUMPDEST ", 
  "PUSH2 0x073a ", 
  "PUSH1 0x04 ", 
  "DUP1 ", 
  "DUP1 ", 
  "CALLDATALOAD ", 
  "SWAP1 ", 
  "PUSH1 0x20 ", 
  "ADD ", 
  "SWAP1 ", 
  "SWAP2 ", 
  "SWAP1 ", 
  "DUP1 ", 
  "CALLDATALOAD ", 
  "SWAP1 ", 
  "PUSH1 0x20 ", 
  "ADD ", 
  "SWAP1 ", 
  "SWAP2 ", 
  "SWAP1 ", 
  "POP ", 
  "POP ", 
  "PUSH2 0x14f5 ", 
  "JUMP ", 
  "JUMPDEST ", 
  "PUSH1 0x40 ", 
  "MLOAD ", 
  "DUP1 ", 
  "DUP3 ", 
  "DUP2 ", 
  "MSTORE ", 
  "PUSH1 0x20 ", 
  "ADD ", 
  "SWAP2 ", 
  "POP ", 
  "POP ", 
  "PUSH1 0x40 ", 
  "MLOAD ", 
  "DUP1 ", 
  "SWAP2 ", 
  "SUB ", 
  "SWAP1 ", 
  "RETURN ", 
  "JUMPDEST ", 
  "CALLVALUE ", 
  "ISZERO ", 
  "PUSH2 0x075b ", 
  "JUMPI ", 
  "PUSH1 0x00 ", 
  "DUP1 ", 
  "REVERT ", 
  "JUMPDEST ", 
  "PUSH2 0x0787 ", 
  "PUSH1 0x04 ", 
  "DUP1 ", 
  "DUP1 ", 
  "CALLDATALOAD ", 
  "PUSH20 0xffffffffffffffffffffffffffffffffffffffff ", 
  "AND ", 
  "SWAP1 ", 
  "PUSH1 0x20 ", 
  "ADD ", 
  "SWAP1 ", 
  "SWAP2 ", 
  "SWAP1 ", 
  "POP ", 
  "POP ", 
  "PUSH2 0x1511 ", 
  "JUMP ", 
  "JUMPDEST ", 
  "STOP "
 ], 
 "overflow": false, 
 "money_concurrency": false, 
 "truncation": false
},"Owned-1":{
 "execution_paths": "12", 
 "callstack": false, 
 "reentrancy": false, 
 "modulo": false, 
 "division": false, 
 "execution_time": "0.815320968628", 
 "signedness": false, 
 "evm_code_coverage": "99.7", 
 "underflow": false, 
 "time_dependency": false, 
 "assertion_failure": false, 
 "timeout": false, 
 "dead_code": [
  "STOP "
 ], 
 "overflow": false, 
 "money_concurrency": false, 
 "truncation": false
},"SafeMath-1":{
 "execution_paths": "16", 
 "callstack": false, 
 "reentrancy": false, 
 "modulo": false, 
 "division": false, 
 "execution_time": "10.9601609707", 
 "signedness": false, 
 "evm_code_coverage": "99.7", 
 "underflow": false, 
 "time_dependency": false, 
 "assertion_failure": false, 
 "timeout": false, 
 "dead_code": [
  "STOP "
 ], 
 "overflow": false, 
 "money_concurrency": false, 
 "truncation": false
},"Hubscop-2":{
 "execution_paths": "62", 
 "callstack": false, 
 "reentrancy": false, 
 "modulo": false, 
 "division": false, 
 "execution_time": "50.1165850163", 
 "signedness": false, 
 "evm_code_coverage": "78.2", 
 "underflow": "\n./0x001fc4a7f2f586596308091c7b296d4535a25a90_ext.sol:Hubscop:103:16\n_totalSupply  - balances[address(0)]\n^", 
 "time_dependency": false, 
 "assertion_failure": false, 
 "timeout": true, 
 "dead_code": [
  "DUP1 ", 
  "PUSH4 0xd05c78da ", 
  "EQ ", 
  "PUSH2 0x05b5 ", 
  "JUMPI ", 
  "DUP1 ", 
  "PUSH4 0xd4ee1d90 ", 
  "EQ ", 
  "PUSH2 0x05f5 ", 
  "JUMPI ", 
  "DUP1 ", 
  "PUSH4 0xdc39d06d ", 
  "EQ ", 
  "PUSH2 0x064a ", 
  "JUMPI ", 
  "DUP1 ", 
  "PUSH4 0xdd62ed3e ", 
  "EQ ", 
  "PUSH2 0x06a4 ", 
  "JUMPI ", 
  "DUP1 ", 
  "PUSH4 0xe6cb9013 ", 
  "EQ ", 
  "PUSH2 0x0710 ", 
  "JUMPI ", 
  "DUP1 ", 
  "PUSH4 0xf2fde38b ", 
  "EQ ", 
  "PUSH2 0x0750 ", 
  "JUMPI ", 
  "JUMPDEST ", 
  "PUSH1 0x00 ", 
  "DUP2 ", 
  "DUP4 ", 
  "MUL ", 
  "SWAP1 ", 
  "POP ", 
  "PUSH1 0x00 ", 
  "DUP4 ", 
  "EQ ", 
  "DUP1 ", 
  "PUSH2 0x12eb ", 
  "JUMPI ", 
  "POP ", 
  "DUP2 ", 
  "DUP4 ", 
  "DUP3 ", 
  "DUP2 ", 
  "ISZERO ", 
  "ISZERO ", 
  "PUSH2 0x12e8 ", 
  "JUMPI ", 
  "ASSERTFAIL ", 
  "JUMPDEST ", 
  "DIV ", 
  "EQ ", 
  "JUMPDEST ", 
  "ISZERO ", 
  "ISZERO ", 
  "PUSH2 0x12f6 ", 
  "JUMPI ", 
  "PUSH1 0x00 ", 
  "DUP1 ", 
  "REVERT ", 
  "JUMPDEST ", 
  "SWAP3 ", 
  "SWAP2 ", 
  "POP ", 
  "POP ", 
  "JUMP ", 
  "JUMPDEST ", 
  "PUSH1 0x01 ", 
  "PUSH1 0x00 ", 
  "SWAP1 ", 
  "SLOAD ", 
  "SWAP1 ", 
  "PUSH2 0x0100 ", 
  "EXP ", 
  "SWAP1 ", 
  "DIV ", 
  "PUSH20 0xffffffffffffffffffffffffffffffffffffffff ", 
  "AND ", 
  "DUP2 ", 
  "JUMP ", 
  "JUMPDEST ", 
  "PUSH1 0x00 ", 
  "DUP1 ", 
  "PUSH1 0x00 ", 
  "SWAP1 ", 
  "SLOAD ", 
  "SWAP1 ", 
  "PUSH2 0x0100 ", 
  "EXP ", 
  "SWAP1 ", 
  "DIV ", 
  "PUSH20 0xffffffffffffffffffffffffffffffffffffffff ", 
  "AND ", 
  "PUSH20 0xffffffffffffffffffffffffffffffffffffffff ", 
  "AND ", 
  "CALLER ", 
  "PUSH20 0xffffffffffffffffffffffffffffffffffffffff ", 
  "AND ", 
  "EQ ", 
  "ISZERO ", 
  "ISZERO ", 
  "PUSH2 0x137f ", 
  "JUMPI ", 
  "PUSH1 0x00 ", 
  "DUP1 ", 
  "REVERT ", 
  "JUMPDEST ", 
  "DUP3 ", 
  "PUSH20 0xffffffffffffffffffffffffffffffffffffffff ", 
  "AND ", 
  "PUSH4 0xa9059cbb ", 
  "PUSH1 0x00 ", 
  "DUP1 ", 
  "SWAP1 ", 
  "SLOAD ", 
  "SWAP1 ", 
  "PUSH2 0x0100 ", 
  "EXP ", 
  "SWAP1 ", 
  "DIV ", 
  "PUSH20 0xffffffffffffffffffffffffffffffffffffffff ", 
  "AND ", 
  "DUP5 ", 
  "PUSH1 0x00 ", 
  "PUSH1 0x40 ", 
  "MLOAD ", 
  "PUSH1 0x20 ", 
  "ADD ", 
  "MSTORE ", 
  "PUSH1 0x40 ", 
  "MLOAD ", 
  "DUP4 ", 
  "PUSH4 0xffffffff ", 
  "AND ", 
  "PUSH29 0x0100000000000000000000000000000000000000000000000000000000 ", 
  "MUL ", 
  "DUP2 ", 
  "MSTORE ", 
  "PUSH1 0x04 ", 
  "ADD ", 
  "DUP1 ", 
  "DUP4 ", 
  "PUSH20 0xffffffffffffffffffffffffffffffffffffffff ", 
  "AND ", 
  "PUSH20 0xffffffffffffffffffffffffffffffffffffffff ", 
  "AND ", 
  "DUP2 ", 
  "MSTORE ", 
  "PUSH1 0x20 ", 
  "ADD ", 
  "DUP3 ", 
  "DUP2 ", 
  "MSTORE ", 
  "PUSH1 0x20 ", 
  "ADD ", 
  "SWAP3 ", 
  "POP ", 
  "POP ", 
  "POP ", 
  "PUSH1 0x20 ", 
  "PUSH1 0x40 ", 
  "MLOAD ", 
  "DUP1 ", 
  "DUP4 ", 
  "SUB ", 
  "DUP2 ", 
  "PUSH1 0x00 ", 
  "DUP8 ", 
  "DUP1 ", 
  "EXTCODESIZE ", 
  "ISZERO ", 
  "ISZERO ", 
  "PUSH2 0x144b ", 
  "JUMPI ", 
  "PUSH1 0x00 ", 
  "DUP1 ", 
  "REVERT ", 
  "JUMPDEST ", 
  "PUSH2 0x02c6 ", 
  "GAS ", 
  "SUB ", 
  "CALL ", 
  "ISZERO ", 
  "ISZERO ", 
  "PUSH2 0x145c ", 
  "JUMPI ", 
  "PUSH1 0x00 ", 
  "DUP1 ", 
  "REVERT ", 
  "JUMPDEST ", 
  "POP ", 
  "POP ", 
  "POP ", 
  "PUSH1 0x40 ", 
  "MLOAD ", 
  "DUP1 ", 
  "MLOAD ", 
  "SWAP1 ", 
  "POP ", 
  "SWAP1 ", 
  "POP ", 
  "SWAP3 ", 
  "SWAP2 ", 
  "POP ", 
  "POP ", 
  "JUMP ", 
  "JUMPDEST ", 
  "PUSH1 0x00 ", 
  "PUSH1 0x07 ", 
  "PUSH1 0x00 ", 
  "DUP5 ", 
  "PUSH20 0xffffffffffffffffffffffffffffffffffffffff ", 
  "AND ", 
  "PUSH20 0xffffffffffffffffffffffffffffffffffffffff ", 
  "AND ", 
  "DUP2 ", 
  "MSTORE ", 
  "PUSH1 0x20 ", 
  "ADD ", 
  "SWAP1 ", 
  "DUP2 ", 
  "MSTORE ", 
  "PUSH1 0x20 ", 
  "ADD ", 
  "PUSH1 0x00 ", 
  "SHA3 ", 
  "PUSH1 0x00 ", 
  "DUP4 ", 
  "PUSH20 0xffffffffffffffffffffffffffffffffffffffff ", 
  "AND ", 
  "PUSH20 0xffffffffffffffffffffffffffffffffffffffff ", 
  "AND ", 
  "DUP2 ", 
  "MSTORE ", 
  "PUSH1 0x20 ", 
  "ADD ", 
  "SWAP1 ", 
  "DUP2 ", 
  "MSTORE ", 
  "PUSH1 0x20 ", 
  "ADD ", 
  "PUSH1 0x00 ", 
  "SHA3 ", 
  "SLOAD ", 
  "SWAP1 ", 
  "POP ", 
  "SWAP3 ", 
  "SWAP2 ", 
  "POP ", 
  "POP ", 
  "JUMP ", 
  "JUMPDEST ", 
  "PUSH1 0x00 ", 
  "DUP1 ", 
  "SWAP1 ", 
  "SLOAD ", 
  "SWAP1 ", 
  "PUSH2 0x0100 ", 
  "EXP ", 
  "SWAP1 ", 
  "DIV ", 
  "PUSH20 0xffffffffffffffffffffffffffffffffffffffff ", 
  "PUSH1 0x00 ", 
  "DUP1 ", 
  "REVERT ", 
  "AND ", 
  "PUSH20 0xffffffffffffffffffffffffffffffffffffffff ", 
  "AND ", 
  "CALLER ", 
  "PUSH20 0xffffffffffffffffffffffffffffffffffffffff ", 
  "AND ", 
  "EQ ", 
  "ISZERO ", 
  "ISZERO ", 
  "PUSH2 0x156c ", 
  "JUMPI ", 
  "PUSH1 0x00 ", 
  "DUP1 ", 
  "REVERT ", 
  "JUMPDEST ", 
  "DUP1 ", 
  "PUSH1 0x01 ", 
  "PUSH1 0x00 ", 
  "PUSH2 0x0100 ", 
  "EXP ", 
  "DUP2 ", 
  "SLOAD ", 
  "DUP2 ", 
  "PUSH20 0xffffffffffffffffffffffffffffffffffffffff ", 
  "MUL ", 
  "NOT ", 
  "AND ", 
  "SWAP1 ", 
  "DUP4 ", 
  "PUSH20 0xffffffffffffffffffffffffffffffffffffffff ", 
  "AND ", 
  "MUL ", 
  "OR ", 
  "SWAP1 ", 
  "SSTORE ", 
  "POP ", 
  "POP ", 
  "JUMP ", 
  "STOP ", 
  "JUMPDEST ", 
  "CALLVALUE ", 
  "ISZERO ", 
  "PUSH2 0x05c0 ", 
  "JUMPI ", 
  "PUSH1 0x00 ", 
  "DUP1 ", 
  "REVERT ", 
  "JUMPDEST ", 
  "PUSH2 0x05df ", 
  "PUSH1 0x04 ", 
  "DUP1 ", 
  "DUP1 ", 
  "CALLDATALOAD ", 
  "SWAP1 ", 
  "PUSH1 0x20 ", 
  "ADD ", 
  "SWAP1 ", 
  "SWAP2 ", 
  "SWAP1 ", 
  "DUP1 ", 
  "CALLDATALOAD ", 
  "SWAP1 ", 
  "PUSH1 0x20 ", 
  "ADD ", 
  "SWAP1 ", 
  "SWAP2 ", 
  "SWAP1 ", 
  "POP ", 
  "POP ", 
  "PUSH2 0x12cb ", 
  "JUMP ", 
  "JUMPDEST ", 
  "PUSH1 0x40 ", 
  "MLOAD ", 
  "DUP1 ", 
  "DUP3 ", 
  "DUP2 ", 
  "MSTORE ", 
  "PUSH1 0x20 ", 
  "ADD ", 
  "SWAP2 ", 
  "POP ", 
  "POP ", 
  "PUSH1 0x40 ", 
  "MLOAD ", 
  "DUP1 ", 
  "SWAP2 ", 
  "SUB ", 
  "SWAP1 ", 
  "RETURN ", 
  "JUMPDEST ", 
  "CALLVALUE ", 
  "ISZERO ", 
  "PUSH2 0x0600 ", 
  "JUMPI ", 
  "PUSH1 0x00 ", 
  "DUP1 ", 
  "REVERT ", 
  "JUMPDEST ", 
  "PUSH2 0x0608 ", 
  "PUSH2 0x12fc ", 
  "JUMP ", 
  "JUMPDEST ", 
  "PUSH1 0x40 ", 
  "MLOAD ", 
  "DUP1 ", 
  "DUP3 ", 
  "PUSH20 0xffffffffffffffffffffffffffffffffffffffff ", 
  "AND ", 
  "PUSH20 0xffffffffffffffffffffffffffffffffffffffff ", 
  "AND ", 
  "DUP2 ", 
  "MSTORE ", 
  "PUSH1 0x20 ", 
  "ADD ", 
  "SWAP2 ", 
  "POP ", 
  "POP ", 
  "PUSH1 0x40 ", 
  "MLOAD ", 
  "DUP1 ", 
  "SWAP2 ", 
  "SUB ", 
  "SWAP1 ", 
  "RETURN ", 
  "JUMPDEST ", 
  "CALLVALUE ", 
  "ISZERO ", 
  "PUSH2 0x0655 ", 
  "JUMPI ", 
  "PUSH1 0x00 ", 
  "DUP1 ", 
  "REVERT ", 
  "JUMPDEST ", 
  "PUSH2 0x068a ", 
  "PUSH1 0x04 ", 
  "DUP1 ", 
  "DUP1 ", 
  "CALLDATALOAD ", 
  "PUSH20 0xffffffffffffffffffffffffffffffffffffffff ", 
  "AND ", 
  "SWAP1 ", 
  "PUSH1 0x20 ", 
  "ADD ", 
  "SWAP1 ", 
  "SWAP2 ", 
  "SWAP1 ", 
  "DUP1 ", 
  "CALLDATALOAD ", 
  "SWAP1 ", 
  "PUSH1 0x20 ", 
  "ADD ", 
  "SWAP1 ", 
  "SWAP2 ", 
  "SWAP1 ", 
  "POP ", 
  "POP ", 
  "PUSH2 0x1322 ", 
  "JUMP ", 
  "JUMPDEST ", 
  "PUSH1 0x40 ", 
  "MLOAD ", 
  "DUP1 ", 
  "DUP3 ", 
  "ISZERO ", 
  "ISZERO ", 
  "ISZERO ", 
  "ISZERO ", 
  "DUP2 ", 
  "MSTORE ", 
  "PUSH1 0x20 ", 
  "ADD ", 
  "SWAP2 ", 
  "POP ", 
  "POP ", 
  "PUSH1 0x40 ", 
  "MLOAD ", 
  "DUP1 ", 
  "SWAP2 ", 
  "SUB ", 
  "SWAP1 ", 
  "RETURN ", 
  "JUMPDEST ", 
  "CALLVALUE ", 
  "ISZERO ", 
  "PUSH2 0x06af ", 
  "JUMPI ", 
  "PUSH1 0x00 ", 
  "DUP1 ", 
  "REVERT ", 
  "JUMPDEST ", 
  "PUSH2 0x06fa ", 
  "PUSH1 0x04 ", 
  "DUP1 ", 
  "DUP1 ", 
  "CALLDATALOAD ", 
  "PUSH20 0xffffffffffffffffffffffffffffffffffffffff ", 
  "AND ", 
  "SWAP1 ", 
  "PUSH1 0x20 ", 
  "ADD ", 
  "SWAP1 ", 
  "SWAP2 ", 
  "SWAP1 ", 
  "DUP1 ", 
  "CALLDATALOAD ", 
  "PUSH20 0xffffffffffffffffffffffffffffffffffffffff ", 
  "AND ", 
  "SWAP1 ", 
  "PUSH1 0x20 ", 
  "ADD ", 
  "SWAP1 ", 
  "SWAP2 ", 
  "SWAP1 ", 
  "POP ", 
  "POP ", 
  "PUSH2 0x146e ", 
  "JUMP ", 
  "JUMPDEST ", 
  "PUSH1 0x40 ", 
  "MLOAD ", 
  "DUP1 ", 
  "DUP3 ", 
  "DUP2 ", 
  "MSTORE ", 
  "PUSH1 0x20 ", 
  "ADD ", 
  "SWAP2 ", 
  "POP ", 
  "POP ", 
  "PUSH1 0x40 ", 
  "MLOAD ", 
  "DUP1 ", 
  "SWAP2 ", 
  "SUB ", 
  "SWAP1 ", 
  "RETURN ", 
  "JUMPDEST ", 
  "CALLVALUE ", 
  "ISZERO ", 
  "PUSH2 0x071b ", 
  "JUMPI ", 
  "PUSH1 0x00 ", 
  "DUP1 ", 
  "REVERT ", 
  "JUMPDEST ", 
  "PUSH2 0x073a ", 
  "PUSH1 0x04 ", 
  "DUP1 ", 
  "DUP1 ", 
  "CALLDATALOAD ", 
  "SWAP1 ", 
  "PUSH1 0x20 ", 
  "ADD ", 
  "SWAP1 ", 
  "SWAP2 ", 
  "SWAP1 ", 
  "DUP1 ", 
  "CALLDATALOAD ", 
  "SWAP1 ", 
  "PUSH1 0x20 ", 
  "ADD ", 
  "SWAP1 ", 
  "SWAP2 ", 
  "SWAP1 ", 
  "POP ", 
  "POP ", 
  "PUSH2 0x14f5 ", 
  "JUMP ", 
  "JUMPDEST ", 
  "PUSH1 0x40 ", 
  "MLOAD ", 
  "DUP1 ", 
  "DUP3 ", 
  "DUP2 ", 
  "MSTORE ", 
  "PUSH1 0x20 ", 
  "ADD ", 
  "SWAP2 ", 
  "POP ", 
  "POP ", 
  "PUSH1 0x40 ", 
  "MLOAD ", 
  "DUP1 ", 
  "SWAP2 ", 
  "SUB ", 
  "SWAP1 ", 
  "RETURN ", 
  "JUMPDEST ", 
  "CALLVALUE ", 
  "ISZERO ", 
  "PUSH2 0x075b ", 
  "JUMPI ", 
  "PUSH1 0x00 ", 
  "DUP1 ", 
  "REVERT ", 
  "JUMPDEST ", 
  "PUSH2 0x0787 ", 
  "PUSH1 0x04 ", 
  "DUP1 ", 
  "DUP1 ", 
  "CALLDATALOAD ", 
  "PUSH20 0xffffffffffffffffffffffffffffffffffffffff ", 
  "AND ", 
  "SWAP1 ", 
  "PUSH1 0x20 ", 
  "ADD ", 
  "SWAP1 ", 
  "SWAP2 ", 
  "SWAP1 ", 
  "POP ", 
  "POP ", 
  "PUSH2 0x1511 ", 
  "JUMP ", 
  "JUMPDEST ", 
  "STOP "
 ], 
 "overflow": false, 
 "money_concurrency": false, 
 "truncation": false
},"Owned-2":{
 "execution_paths": "12", 
 "callstack": false, 
 "reentrancy": false, 
 "modulo": false, 
 "division": false, 
 "execution_time": "0.693439006805", 
 "signedness": false, 
 "evm_code_coverage": "99.7", 
 "underflow": false, 
 "time_dependency": false, 
 "assertion_failure": false, 
 "timeout": false, 
 "dead_code": [
  "STOP "
 ], 
 "overflow": false, 
 "money_concurrency": false, 
 "truncation": false
},"SafeMath-2":{
 "execution_paths": "16", 
 "callstack": false, 
 "reentrancy": false, 
 "modulo": false, 
 "division": false, 
 "execution_time": "9.77711200714", 
 "signedness": false, 
 "evm_code_coverage": "99.7", 
 "underflow": false, 
 "time_dependency": false, 
 "assertion_failure": false, 
 "timeout": false, 
 "dead_code": [
  "STOP "
 ], 
 "overflow": false, 
 "money_concurrency": false, 
 "truncation": false
},"Hubscop-3":{
 "execution_paths": "65", 
 "callstack": false, 
 "reentrancy": false, 
 "modulo": false, 
 "division": false, 
 "execution_time": "50.1085848808", 
 "signedness": false, 
 "evm_code_coverage": "78.4", 
 "underflow": "\n./0x001fc4a7f2f586596308091c7b296d4535a25a90_ext.sol:Hubscop:103:16\n_totalSupply  - balances[address(0)]\n^", 
 "time_dependency": false, 
 "assertion_failure": false, 
 "timeout": true, 
 "dead_code": [
  "DUP1 ", 
  "PUSH4 0xd05c78da ", 
  "EQ ", 
  "PUSH2 0x05b5 ", 
  "JUMPI ", 
  "DUP1 ", 
  "PUSH4 0xd4ee1d90 ", 
  "EQ ", 
  "PUSH2 0x05f5 ", 
  "JUMPI ", 
  "DUP1 ", 
  "PUSH4 0xdc39d06d ", 
  "EQ ", 
  "PUSH2 0x064a ", 
  "JUMPI ", 
  "DUP1 ", 
  "PUSH4 0xdd62ed3e ", 
  "EQ ", 
  "PUSH2 0x06a4 ", 
  "JUMPI ", 
  "DUP1 ", 
  "PUSH4 0xe6cb9013 ", 
  "EQ ", 
  "PUSH2 0x0710 ", 
  "JUMPI ", 
  "DUP1 ", 
  "PUSH4 0xf2fde38b ", 
  "EQ ", 
  "PUSH2 0x0750 ", 
  "JUMPI ", 
  "AND ", 
  "JUMPDEST ", 
  "PUSH1 0x00 ", 
  "DUP2 ", 
  "DUP4 ", 
  "MUL ", 
  "SWAP1 ", 
  "POP ", 
  "PUSH1 0x00 ", 
  "DUP4 ", 
  "EQ ", 
  "DUP1 ", 
  "PUSH2 0x12e7 ", 
  "JUMPI ", 
  "POP ", 
  "DUP2 ", 
  "DUP4 ", 
  "DUP3 ", 
  "DUP2 ", 
  "ISZERO ", 
  "ISZERO ", 
  "PUSH2 0x12e4 ", 
  "JUMPI ", 
  "ASSERTFAIL ", 
  "JUMPDEST ", 
  "DIV ", 
  "EQ ", 
  "JUMPDEST ", 
  "ISZERO ", 
  "ISZERO ", 
  "PUSH2 0x12f2 ", 
  "JUMPI ", 
  "PUSH1 0x00 ", 
  "DUP1 ", 
  "REVERT ", 
  "JUMPDEST ", 
  "SWAP3 ", 
  "SWAP2 ", 
  "POP ", 
  "POP ", 
  "JUMP ", 
  "JUMPDEST ", 
  "PUSH1 0x01 ", 
  "PUSH1 0x00 ", 
  "SWAP1 ", 
  "SLOAD ", 
  "SWAP1 ", 
  "PUSH2 0x0100 ", 
  "EXP ", 
  "SWAP1 ", 
  "DIV ", 
  "PUSH20 0xffffffffffffffffffffffffffffffffffffffff ", 
  "AND ", 
  "DUP2 ", 
  "JUMP ", 
  "JUMPDEST ", 
  "PUSH1 0x00 ", 
  "DUP1 ", 
  "PUSH1 0x00 ", 
  "SWAP1 ", 
  "SLOAD ", 
  "SWAP1 ", 
  "PUSH2 0x0100 ", 
  "EXP ", 
  "SWAP1 ", 
  "DIV ", 
  "PUSH20 0xffffffffffffffffffffffffffffffffffffffff ", 
  "AND ", 
  "PUSH20 0xffffffffffffffffffffffffffffffffffffffff ", 
  "AND ", 
  "CALLER ", 
  "PUSH20 0xffffffffffffffffffffffffffffffffffffffff ", 
  "AND ", 
  "EQ ", 
  "ISZERO ", 
  "ISZERO ", 
  "PUSH2 0x137b ", 
  "JUMPI ", 
  "PUSH1 0x00 ", 
  "DUP1 ", 
  "REVERT ", 
  "JUMPDEST ", 
  "DUP3 ", 
  "PUSH20 0xffffffffffffffffffffffffffffffffffffffff ", 
  "AND ", 
  "PUSH4 0xa9059cbb ", 
  "PUSH1 0x00 ", 
  "DUP1 ", 
  "SWAP1 ", 
  "SLOAD ", 
  "SWAP1 ", 
  "PUSH2 0x0100 ", 
  "EXP ", 
  "SWAP1 ", 
  "DIV ", 
  "PUSH20 0xffffffffffffffffffffffffffffffffffffffff ", 
  "AND ", 
  "DUP5 ", 
  "PUSH1 0x40 ", 
  "MLOAD ", 
  "DUP4 ", 
  "PUSH4 0xffffffff ", 
  "AND ", 
  "PUSH29 0x0100000000000000000000000000000000000000000000000000000000 ", 
  "MUL ", 
  "DUP2 ", 
  "MSTORE ", 
  "PUSH1 0x04 ", 
  "ADD ", 
  "DUP1 ", 
  "DUP4 ", 
  "PUSH20 0xffffffffffffffffffffffffffffffffffffffff ", 
  "AND ", 
  "PUSH20 0xffffffffffffffffffffffffffffffffffffffff ", 
  "AND ", 
  "DUP2 ", 
  "MSTORE ", 
  "PUSH1 0x20 ", 
  "ADD ", 
  "DUP3 ", 
  "DUP2 ", 
  "MSTORE ", 
  "PUSH1 0x20 ", 
  "ADD ", 
  "SWAP3 ", 
  "POP ", 
  "POP ", 
  "POP ", 
  "PUSH1 0x20 ", 
  "PUSH1 0x40 ", 
  "MLOAD ", 
  "DUP1 ", 
  "DUP4 ", 
  "SUB ", 
  "DUP2 ", 
  "PUSH1 0x00 ", 
  "DUP8 ", 
  "DUP1 ", 
  "EXTCODESIZE ", 
  "ISZERO ", 
  "ISZERO ", 
  "PUSH2 0x143e ", 
  "JUMPI ", 
  "PUSH1 0x00 ", 
  "DUP1 ", 
  "REVERT ", 
  "JUMPDEST ", 
  "GAS ", 
  "CALL ", 
  "ISZERO ", 
  "ISZERO ", 
  "PUSH2 0x144b ", 
  "JUMPI ", 
  "PUSH1 0x00 ", 
  "DUP1 ", 
  "REVERT ", 
  "JUMPDEST ", 
  "POP ", 
  "POP ", 
  "POP ", 
  "PUSH1 0x40 ", 
  "MLOAD ", 
  "DUP1 ", 
  "MLOAD ", 
  "SWAP1 ", 
  "POP ", 
  "SWAP1 ", 
  "POP ", 
  "SWAP3 ", 
  "SWAP2 ", 
  "POP ", 
  "POP ", 
  "JUMP ", 
  "JUMPDEST ", 
  "PUSH1 0x00 ", 
  "PUSH1 0x07 ", 
  "PUSH1 0x00 ", 
  "DUP5 ", 
  "PUSH20 0xffffffffffffffffffffffffffffffffffffffff ", 
  "AND ", 
  "PUSH20 0xffffffffffffffffffffffffffffffffffffffff ", 
  "AND ", 
  "DUP2 ", 
  "MSTORE ", 
  "PUSH1 0x20 ", 
  "ADD ", 
  "SWAP1 ", 
  "DUP2 ", 
  "MSTORE ", 
  "PUSH1 0x20 ", 
  "ADD ", 
  "PUSH1 0x00 ", 
  "SHA3 ", 
  "PUSH1 0x00 ", 
  "DUP4 ", 
  "PUSH20 0xffffffffffffffffffffffffffffffffffffffff ", 
  "AND ", 
  "PUSH20 0xffffffffffffffffffffffffffffffffffffffff ", 
  "AND ", 
  "DUP2 ", 
  "MSTORE ", 
  "PUSH1 0x20 ", 
  "ADD ", 
  "SWAP1 ", 
  "DUP2 ", 
  "MSTORE ", 
  "PUSH1 0x20 ", 
  "ADD ", 
  "PUSH1 0x00 ", 
  "SHA3 ", 
  "SLOAD ", 
  "SWAP1 ", 
  "POP ", 
  "SWAP3 ", 
  "SWAP2 ", 
  "POP ", 
  "POP ", 
  "JUMP ", 
  "JUMPDEST ", 
  "PUSH1 0x00 ", 
  "DUP1 ", 
  "SWAP1 ", 
  "SLOAD ", 
  "SWAP1 ", 
  "PUSH2 0x0100 ", 
  "EXP ", 
  "SWAP1 ", 
  "DIV ", 
  "PUSH20 0xffffffffffffffffffffffffffffffffffffffff ", 
  "PUSH1 0x00 ", 
  "DUP1 ", 
  "REVERT ", 
  "PUSH20 0xffffffffffffffffffffffffffffffffffffffff ", 
  "AND ", 
  "CALLER ", 
  "PUSH20 0xffffffffffffffffffffffffffffffffffffffff ", 
  "AND ", 
  "EQ ", 
  "ISZERO ", 
  "ISZERO ", 
  "PUSH2 0x155b ", 
  "JUMPI ", 
  "PUSH1 0x00 ", 
  "DUP1 ", 
  "REVERT ", 
  "JUMPDEST ", 
  "DUP1 ", 
  "PUSH1 0x01 ", 
  "PUSH1 0x00 ", 
  "PUSH2 0x0100 ", 
  "EXP ", 
  "DUP2 ", 
  "SLOAD ", 
  "DUP2 ", 
  "PUSH20 0xffffffffffffffffffffffffffffffffffffffff ", 
  "MUL ", 
  "NOT ", 
  "AND ", 
  "SWAP1 ", 
  "DUP4 ", 
  "PUSH20 0xffffffffffffffffffffffffffffffffffffffff ", 
  "AND ", 
  "MUL ", 
  "OR ", 
  "SWAP1 ", 
  "SSTORE ", 
  "POP ", 
  "POP ", 
  "JUMP ", 
  "STOP ", 
  "JUMPDEST ", 
  "CALLVALUE ", 
  "ISZERO ", 
  "PUSH2 0x05c0 ", 
  "JUMPI ", 
  "PUSH1 0x00 ", 
  "DUP1 ", 
  "REVERT ", 
  "JUMPDEST ", 
  "PUSH2 0x05df ", 
  "PUSH1 0x04 ", 
  "DUP1 ", 
  "DUP1 ", 
  "CALLDATALOAD ", 
  "SWAP1 ", 
  "PUSH1 0x20 ", 
  "ADD ", 
  "SWAP1 ", 
  "SWAP2 ", 
  "SWAP1 ", 
  "DUP1 ", 
  "CALLDATALOAD ", 
  "SWAP1 ", 
  "PUSH1 0x20 ", 
  "ADD ", 
  "SWAP1 ", 
  "SWAP2 ", 
  "SWAP1 ", 
  "POP ", 
  "POP ", 
  "PUSH2 0x12c7 ", 
  "JUMP ", 
  "JUMPDEST ", 
  "PUSH1 0x40 ", 
  "MLOAD ", 
  "DUP1 ", 
  "DUP3 ", 
  "DUP2 ", 
  "MSTORE ", 
  "PUSH1 0x20 ", 
  "ADD ", 
  "SWAP2 ", 
  "POP ", 
  "POP ", 
  "PUSH1 0x40 ", 
  "MLOAD ", 
  "DUP1 ", 
  "SWAP2 ", 
  "SUB ", 
  "SWAP1 ", 
  "RETURN ", 
  "JUMPDEST ", 
  "CALLVALUE ", 
  "ISZERO ", 
  "PUSH2 0x0600 ", 
  "JUMPI ", 
  "PUSH1 0x00 ", 
  "DUP1 ", 
  "REVERT ", 
  "JUMPDEST ", 
  "PUSH2 0x0608 ", 
  "PUSH2 0x12f8 ", 
  "JUMP ", 
  "JUMPDEST ", 
  "PUSH1 0x40 ", 
  "MLOAD ", 
  "DUP1 ", 
  "DUP3 ", 
  "PUSH20 0xffffffffffffffffffffffffffffffffffffffff ", 
  "AND ", 
  "PUSH20 0xffffffffffffffffffffffffffffffffffffffff ", 
  "AND ", 
  "DUP2 ", 
  "MSTORE ", 
  "PUSH1 0x20 ", 
  "ADD ", 
  "SWAP2 ", 
  "POP ", 
  "POP ", 
  "PUSH1 0x40 ", 
  "MLOAD ", 
  "DUP1 ", 
  "SWAP2 ", 
  "SUB ", 
  "SWAP1 ", 
  "RETURN ", 
  "JUMPDEST ", 
  "CALLVALUE ", 
  "ISZERO ", 
  "PUSH2 0x0655 ", 
  "JUMPI ", 
  "PUSH1 0x00 ", 
  "DUP1 ", 
  "REVERT ", 
  "JUMPDEST ", 
  "PUSH2 0x068a ", 
  "PUSH1 0x04 ", 
  "DUP1 ", 
  "DUP1 ", 
  "CALLDATALOAD ", 
  "PUSH20 0xffffffffffffffffffffffffffffffffffffffff ", 
  "AND ", 
  "SWAP1 ", 
  "PUSH1 0x20 ", 
  "ADD ", 
  "SWAP1 ", 
  "SWAP2 ", 
  "SWAP1 ", 
  "DUP1 ", 
  "CALLDATALOAD ", 
  "SWAP1 ", 
  "PUSH1 0x20 ", 
  "ADD ", 
  "SWAP1 ", 
  "SWAP2 ", 
  "SWAP1 ", 
  "POP ", 
  "POP ", 
  "PUSH2 0x131e ", 
  "JUMP ", 
  "JUMPDEST ", 
  "PUSH1 0x40 ", 
  "MLOAD ", 
  "DUP1 ", 
  "DUP3 ", 
  "ISZERO ", 
  "ISZERO ", 
  "ISZERO ", 
  "ISZERO ", 
  "DUP2 ", 
  "MSTORE ", 
  "PUSH1 0x20 ", 
  "ADD ", 
  "SWAP2 ", 
  "POP ", 
  "POP ", 
  "PUSH1 0x40 ", 
  "MLOAD ", 
  "DUP1 ", 
  "SWAP2 ", 
  "SUB ", 
  "SWAP1 ", 
  "RETURN ", 
  "JUMPDEST ", 
  "CALLVALUE ", 
  "ISZERO ", 
  "PUSH2 0x06af ", 
  "JUMPI ", 
  "PUSH1 0x00 ", 
  "DUP1 ", 
  "REVERT ", 
  "JUMPDEST ", 
  "PUSH2 0x06fa ", 
  "PUSH1 0x04 ", 
  "DUP1 ", 
  "DUP1 ", 
  "CALLDATALOAD ", 
  "PUSH20 0xffffffffffffffffffffffffffffffffffffffff ", 
  "AND ", 
  "SWAP1 ", 
  "PUSH1 0x20 ", 
  "ADD ", 
  "SWAP1 ", 
  "SWAP2 ", 
  "SWAP1 ", 
  "DUP1 ", 
  "CALLDATALOAD ", 
  "PUSH20 0xffffffffffffffffffffffffffffffffffffffff ", 
  "AND ", 
  "SWAP1 ", 
  "PUSH1 0x20 ", 
  "ADD ", 
  "SWAP1 ", 
  "SWAP2 ", 
  "SWAP1 ", 
  "POP ", 
  "POP ", 
  "PUSH2 0x145d ", 
  "JUMP ", 
  "JUMPDEST ", 
  "PUSH1 0x40 ", 
  "MLOAD ", 
  "DUP1 ", 
  "DUP3 ", 
  "DUP2 ", 
  "MSTORE ", 
  "PUSH1 0x20 ", 
  "ADD ", 
  "SWAP2 ", 
  "POP ", 
  "POP ", 
  "PUSH1 0x40 ", 
  "MLOAD ", 
  "DUP1 ", 
  "SWAP2 ", 
  "SUB ", 
  "SWAP1 ", 
  "RETURN ", 
  "JUMPDEST ", 
  "CALLVALUE ", 
  "ISZERO ", 
  "PUSH2 0x071b ", 
  "JUMPI ", 
  "PUSH1 0x00 ", 
  "DUP1 ", 
  "REVERT ", 
  "JUMPDEST ", 
  "PUSH2 0x073a ", 
  "PUSH1 0x04 ", 
  "DUP1 ", 
  "DUP1 ", 
  "CALLDATALOAD ", 
  "SWAP1 ", 
  "PUSH1 0x20 ", 
  "ADD ", 
  "SWAP1 ", 
  "SWAP2 ", 
  "SWAP1 ", 
  "DUP1 ", 
  "CALLDATALOAD ", 
  "SWAP1 ", 
  "PUSH1 0x20 ", 
  "ADD ", 
  "SWAP1 ", 
  "SWAP2 ", 
  "SWAP1 ", 
  "POP ", 
  "POP ", 
  "PUSH2 0x14e4 ", 
  "JUMP ", 
  "JUMPDEST ", 
  "PUSH1 0x40 ", 
  "MLOAD ", 
  "DUP1 ", 
  "DUP3 ", 
  "DUP2 ", 
  "MSTORE ", 
  "PUSH1 0x20 ", 
  "ADD ", 
  "SWAP2 ", 
  "POP ", 
  "POP ", 
  "PUSH1 0x40 ", 
  "MLOAD ", 
  "DUP1 ", 
  "SWAP2 ", 
  "SUB ", 
  "SWAP1 ", 
  "RETURN ", 
  "JUMPDEST ", 
  "CALLVALUE ", 
  "ISZERO ", 
  "PUSH2 0x075b ", 
  "JUMPI ", 
  "PUSH1 0x00 ", 
  "DUP1 ", 
  "REVERT ", 
  "JUMPDEST ", 
  "PUSH2 0x0787 ", 
  "PUSH1 0x04 ", 
  "DUP1 ", 
  "DUP1 ", 
  "CALLDATALOAD ", 
  "PUSH20 0xffffffffffffffffffffffffffffffffffffffff ", 
  "AND ", 
  "SWAP1 ", 
  "PUSH1 0x20 ", 
  "ADD ", 
  "SWAP1 ", 
  "SWAP2 ", 
  "SWAP1 ", 
  "POP ", 
  "POP ", 
  "PUSH2 0x1500 ", 
  "JUMP ", 
  "JUMPDEST ", 
  "STOP "
 ], 
 "overflow": false, 
 "money_concurrency": false, 
 "truncation": false
},"Owned-3":{
 "execution_paths": "12", 
 "callstack": false, 
 "reentrancy": false, 
 "modulo": false, 
 "division": false, 
 "execution_time": "0.555944919586", 
 "signedness": false, 
 "evm_code_coverage": "99.7", 
 "underflow": false, 
 "time_dependency": false, 
 "assertion_failure": false, 
 "timeout": false, 
 "dead_code": [
  "STOP "
 ], 
 "overflow": false, 
 "money_concurrency": false, 
 "truncation": false
},"SafeMath-3":{
 "execution_paths": "16", 
 "callstack": false, 
 "reentrancy": false, 
 "modulo": false, 
 "division": false, 
 "execution_time": "10.0790929794", 
 "signedness": false, 
 "evm_code_coverage": "99.7", 
 "underflow": false, 
 "time_dependency": false, 
 "assertion_failure": false, 
 "timeout": false, 
 "dead_code": [
  "STOP "
 ], 
 "overflow": false, 
 "money_concurrency": false, 
 "truncation": false
},"Hubscop-4":{
 "execution_paths": "65", 
 "callstack": false, 
 "reentrancy": false, 
 "modulo": false, 
 "division": false, 
 "execution_time": "50.0801570415", 
 "signedness": false, 
 "evm_code_coverage": "76.8", 
 "underflow": "\n./0x001fc4a7f2f586596308091c7b296d4535a25a90_ext.sol:Hubscop:103:16\n_totalSupply  - balances[address(0)]\n^", 
 "time_dependency": false, 
 "assertion_failure": false, 
 "timeout": true, 
 "dead_code": [
  "AND ", 
  "SWAP1 ", 
  "PUSH1 0x20 ", 
  "ADD ", 
  "SWAP1 ", 
  "SWAP3 ", 
  "SWAP2 ", 
  "SWAP1 ", 
  "POP ", 
  "POP ", 
  "POP ", 
  "PUSH2 0x15c4 ", 
  "JUMP ", 
  "JUMPDEST ", 
  "STOP ", 
  "JUMP ", 
  "REVERT ", 
  "JUMPDEST ", 
  "DUP1 ", 
  "POP ", 
  "PUSH1 0x01 ", 
  "DUP1 ", 
  "PUSH4 0xd05c78da ", 
  "EQ ", 
  "PUSH2 0x0613 ", 
  "JUMPI ", 
  "DUP1 ", 
  "PUSH4 0xd4ee1d90 ", 
  "EQ ", 
  "PUSH2 0x065e ", 
  "JUMPI ", 
  "DUP1 ", 
  "PUSH4 0xdc39d06d ", 
  "EQ ", 
  "PUSH2 0x06b5 ", 
  "JUMPI ", 
  "DUP1 ", 
  "PUSH4 0xdd62ed3e ", 
  "EQ ", 
  "PUSH2 0x071a ", 
  "JUMPI ", 
  "DUP1 ", 
  "PUSH4 0xe6cb9013 ", 
  "EQ ", 
  "PUSH2 0x0791 ", 
  "JUMPI ", 
  "DUP1 ", 
  "PUSH4 0xf2fde38b ", 
  "EQ ", 
  "PUSH2 0x07dc ", 
  "JUMPI ", 
  "EXP ", 
  "SWAP1 ", 
  "DUP2 ", 
  "SLOAD ", 
  "DUP2 ", 
  "PUSH20 0xffffffffffffffffffffffffffffffffffffffff ", 
  "JUMPDEST ", 
  "PUSH1 0x00 ", 
  "DUP2 ", 
  "DUP4 ", 
  "MUL ", 
  "SWAP1 ", 
  "POP ", 
  "PUSH1 0x00 ", 
  "DUP4 ", 
  "EQ ", 
  "DUP1 ", 
  "PUSH2 0x1386 ", 
  "JUMPI ", 
  "POP ", 
  "DUP2 ", 
  "DUP4 ", 
  "DUP3 ", 
  "DUP2 ", 
  "ISZERO ", 
  "ISZERO ", 
  "PUSH2 0x1383 ", 
  "JUMPI ", 
  "ASSERTFAIL ", 
  "JUMPDEST ", 
  "DIV ", 
  "EQ ", 
  "JUMPDEST ", 
  "ISZERO ", 
  "ISZERO ", 
  "PUSH2 0x1391 ", 
  "JUMPI ", 
  "PUSH1 0x00 ", 
  "DUP1 ", 
  "REVERT ", 
  "JUMPDEST ", 
  "SWAP3 ", 
  "SWAP2 ", 
  "POP ", 
  "POP ", 
  "JUMP ", 
  "JUMPDEST ", 
  "PUSH1 0x01 ", 
  "PUSH1 0x00 ", 
  "SWAP1 ", 
  "SLOAD ", 
  "SWAP1 ", 
  "PUSH2 0x0100 ", 
  "EXP ", 
  "SWAP1 ", 
  "DIV ", 
  "PUSH20 0xffffffffffffffffffffffffffffffffffffffff ", 
  "AND ", 
  "DUP2 ", 
  "JUMP ", 
  "JUMPDEST ", 
  "PUSH1 0x00 ", 
  "DUP1 ", 
  "PUSH1 0x00 ", 
  "SWAP1 ", 
  "SLOAD ", 
  "SWAP1 ", 
  "PUSH2 0x0100 ", 
  "EXP ", 
  "SWAP1 ", 
  "DIV ", 
  "PUSH20 0xffffffffffffffffffffffffffffffffffffffff ", 
  "AND ", 
  "PUSH20 0xffffffffffffffffffffffffffffffffffffffff ", 
  "AND ", 
  "CALLER ", 
  "PUSH20 0xffffffffffffffffffffffffffffffffffffffff ", 
  "AND ", 
  "EQ ", 
  "ISZERO ", 
  "ISZERO ", 
  "PUSH2 0x141a ", 
  "JUMPI ", 
  "PUSH1 0x00 ", 
  "DUP1 ", 
  "REVERT ", 
  "JUMPDEST ", 
  "DUP3 ", 
  "PUSH20 0xffffffffffffffffffffffffffffffffffffffff ", 
  "AND ", 
  "PUSH4 0xa9059cbb ", 
  "PUSH1 0x00 ", 
  "DUP1 ", 
  "SWAP1 ", 
  "SLOAD ", 
  "SWAP1 ", 
  "PUSH2 0x0100 ", 
  "EXP ", 
  "SWAP1 ", 
  "DIV ", 
  "PUSH20 0xffffffffffffffffffffffffffffffffffffffff ", 
  "AND ", 
  "DUP5 ", 
  "PUSH1 0x40 ", 
  "MLOAD ", 
  "DUP4 ", 
  "PUSH4 0xffffffff ", 
  "AND ", 
  "PUSH29 0x0100000000000000000000000000000000000000000000000000000000 ", 
  "AND ", 
  "EQ ", 
  "ISZERO ", 
  "MUL ", 
  "DUP2 ", 
  "MSTORE ", 
  "PUSH1 0x04 ", 
  "ADD ", 
  "DUP1 ", 
  "DUP4 ", 
  "PUSH20 0xffffffffffffffffffffffffffffffffffffffff ", 
  "PUSH2 0x161f ", 
  "AND ", 
  "JUMPI ", 
  "AND ", 
  "PUSH20 0xffffffffffffffffffffffffffffffffffffffff ", 
  "PUSH1 0x00 ", 
  "DUP1 ", 
  "SWAP1 ", 
  "AND ", 
  "DUP2 ", 
  "MSTORE ", 
  "PUSH1 0x20 ", 
  "ADD ", 
  "DUP3 ", 
  "DUP2 ", 
  "MSTORE ", 
  "PUSH1 0x20 ", 
  "ADD ", 
  "SWAP3 ", 
  "POP ", 
  "POP ", 
  "POP ", 
  "PUSH1 0x20 ", 
  "PUSH1 0x40 ", 
  "MLOAD ", 
  "DUP1 ", 
  "DUP4 ", 
  "SUB ", 
  "DUP2 ", 
  "PUSH1 0x00 ", 
  "DUP8 ", 
  "DUP1 ", 
  "EXTCODESIZE ", 
  "ISZERO ", 
  "DUP1 ", 
  "ISZERO ", 
  "PUSH2 0x14de ", 
  "JUMPI ", 
  "PUSH1 0x00 ", 
  "DUP1 ", 
  "REVERT ", 
  "JUMPDEST ", 
  "POP ", 
  "GAS ", 
  "CALL ", 
  "ISZERO ", 
  "DUP1 ", 
  "ISZERO ", 
  "PUSH2 0x14f2 ", 
  "JUMPI ", 
  "RETURNDATASIZE ", 
  "PUSH1 0x00 ", 
  "DUP1 ", 
  "RETURNDATACOPY ", 
  "RETURNDATASIZE ", 
  "PUSH1 0x00 ", 
  "REVERT ", 
  "JUMPDEST ", 
  "POP ", 
  "POP ", 
  "POP ", 
  "POP ", 
  "PUSH1 0x40 ", 
  "MLOAD ", 
  "RETURNDATASIZE ", 
  "PUSH1 0x20 ", 
  "DUP2 ", 
  "LT ", 
  "ISZERO ", 
  "PUSH2 0x1508 ", 
  "JUMPI ", 
  "PUSH1 0x00 ", 
  "DUP1 ", 
  "REVERT ", 
  "JUMPDEST ", 
  "DUP2 ", 
  "ADD ", 
  "SWAP1 ", 
  "DUP1 ", 
  "DUP1 ", 
  "MLOAD ", 
  "SWAP1 ", 
  "PUSH1 0x20 ", 
  "ADD ", 
  "SWAP1 ", 
  "SWAP3 ", 
  "SWAP2 ", 
  "SWAP1 ", 
  "POP ", 
  "POP ", 
  "POP ", 
  "SWAP1 ", 
  "POP ", 
  "SWAP3 ", 
  "SWAP2 ", 
  "POP ", 
  "POP ", 
  "JUMP ", 
  "JUMPDEST ", 
  "PUSH1 0x00 ", 
  "PUSH1 0x07 ", 
  "PUSH1 0x00 ", 
  "DUP5 ", 
  "PUSH20 0xffffffffffffffffffffffffffffffffffffffff ", 
  "AND ", 
  "PUSH20 0xffffffffffffffffffffffffffffffffffffffff ", 
  "AND ", 
  "DUP2 ", 
  "MSTORE ", 
  "PUSH1 0x20 ", 
  "ADD ", 
  "SWAP1 ", 
  "DUP2 ", 
  "MSTORE ", 
  "PUSH1 0x20 ", 
  "ADD ", 
  "PUSH1 0x00 ", 
  "SHA3 ", 
  "PUSH1 0x00 ", 
  "DUP4 ", 
  "PUSH20 0xffffffffffffffffffffffffffffffffffffffff ", 
  "PUSH1 0x00 ", 
  "DUP1 ", 
  "REVERT ", 
  "AND ", 
  "PUSH20 0xffffffffffffffffffffffffffffffffffffffff ", 
  "MUL ", 
  "MUL ", 
  "NOT ", 
  "AND ", 
  "DUP2 ", 
  "MSTORE ", 
  "PUSH1 0x20 ", 
  "ADD ", 
  "SWAP1 ", 
  "DUP2 ", 
  "MSTORE ", 
  "PUSH1 0x20 ", 
  "ADD ", 
  "PUSH1 0x00 ", 
  "SHA3 ", 
  "SLOAD ", 
  "SWAP1 ", 
  "POP ", 
  "SWAP3 ", 
  "SWAP2 ", 
  "POP ", 
  "POP ", 
  "JUMP ", 
  "JUMPDEST ", 
  "PUSH1 0x00 ", 
  "DUP1 ", 
  "SWAP1 ", 
  "SLOAD ", 
  "SWAP1 ", 
  "PUSH2 0x0100 ", 
  "EXP ", 
  "SWAP1 ", 
  "DIV ", 
  "PUSH20 0xffffffffffffffffffffffffffffffffffffffff ", 
  "AND ", 
  "PUSH20 0xffffffffffffffffffffffffffffffffffffffff ", 
  "AND ", 
  "CALLER ", 
  "PUSH20 0xffffffffffffffffffffffffffffffffffffffff ", 
  "JUMPDEST ", 
  "CALLVALUE ", 
  "DUP1 ", 
  "ISZERO ", 
  "PUSH2 0x061f ", 
  "JUMPI ", 
  "PUSH1 0x00 ", 
  "OR ", 
  "DUP1 ", 
  "REVERT ", 
  "JUMPDEST ", 
  "POP ", 
  "PUSH2 0x0648 ", 
  "PUSH1 0x00 ", 
  "PUSH1 0x04 ", 
  "PUSH2 0x0100 ", 
  "DUP1 ", 
  "CALLDATASIZE ", 
  "SUB ", 
  "DUP2 ", 
  "ADD ", 
  "SWAP1 ", 
  "DUP1 ", 
  "DUP1 ", 
  "CALLDATALOAD ", 
  "SWAP1 ", 
  "PUSH1 0x20 ", 
  "ADD ", 
  "SWAP1 ", 
  "SWAP3 ", 
  "SWAP2 ", 
  "SWAP1 ", 
  "DUP1 ", 
  "CALLDATALOAD ", 
  "SWAP1 ", 
  "PUSH1 0x20 ", 
  "SSTORE ", 
  "ADD ", 
  "SWAP1 ", 
  "SWAP3 ", 
  "SWAP2 ", 
  "SWAP1 ", 
  "POP ", 
  "POP ", 
  "POP ", 
  "PUSH2 0x1366 ", 
  "DUP4 ", 
  "PUSH20 0xffffffffffffffffffffffffffffffffffffffff ", 
  "JUMP ", 
  "JUMPDEST ", 
  "PUSH1 0x40 ", 
  "MLOAD ", 
  "DUP1 ", 
  "DUP3 ", 
  "DUP2 ", 
  "MSTORE ", 
  "PUSH1 0x20 ", 
  "ADD ", 
  "SWAP2 ", 
  "POP ", 
  "POP ", 
  "PUSH1 0x40 ", 
  "MLOAD ", 
  "DUP1 ", 
  "SWAP2 ", 
  "SUB ", 
  "SWAP1 ", 
  "RETURN ", 
  "JUMPDEST ", 
  "CALLVALUE ", 
  "DUP1 ", 
  "ISZERO ", 
  "PUSH2 0x066a ", 
  "STOP ", 
  "JUMPI ", 
  "PUSH1 0x00 ", 
  "DUP1 ", 
  "REVERT ", 
  "JUMPDEST ", 
  "POP ", 
  "PUSH2 0x0673 ", 
  "PUSH2 0x1397 ", 
  "JUMP ", 
  "JUMPDEST ", 
  "PUSH1 0x40 ", 
  "MLOAD ", 
  "DUP1 ", 
  "DUP3 ", 
  "PUSH20 0xffffffffffffffffffffffffffffffffffffffff ", 
  "AND ", 
  "PUSH20 0xffffffffffffffffffffffffffffffffffffffff ", 
  "AND ", 
  "DUP2 ", 
  "MSTORE ", 
  "PUSH1 0x20 ", 
  "ADD ", 
  "SWAP2 ", 
  "POP ", 
  "POP ", 
  "PUSH1 0x40 ", 
  "MLOAD ", 
  "DUP1 ", 
  "SWAP2 ", 
  "SUB ", 
  "SWAP1 ", 
  "RETURN ", 
  "JUMPDEST ", 
  "CALLVALUE ", 
  "DUP1 ", 
  "ISZERO ", 
  "PUSH2 0x06c1 ", 
  "JUMPI ", 
  "PUSH1 0x00 ", 
  "DUP1 ", 
  "REVERT ", 
  "JUMPDEST ", 
  "POP ", 
  "PUSH2 0x0700 ", 
  "PUSH1 0x04 ", 
  "DUP1 ", 
  "CALLDATASIZE ", 
  "SUB ", 
  "DUP2 ", 
  "ADD ", 
  "SWAP1 ", 
  "DUP1 ", 
  "DUP1 ", 
  "CALLDATALOAD ", 
  "PUSH20 0xffffffffffffffffffffffffffffffffffffffff ", 
  "AND ", 
  "SWAP1 ", 
  "PUSH1 0x20 ", 
  "ADD ", 
  "SWAP1 ", 
  "SWAP3 ", 
  "SWAP2 ", 
  "SWAP1 ", 
  "DUP1 ", 
  "CALLDATALOAD ", 
  "SWAP1 ", 
  "PUSH1 0x20 ", 
  "ADD ", 
  "SWAP1 ", 
  "SWAP3 ", 
  "SWAP2 ", 
  "SWAP1 ", 
  "POP ", 
  "POP ", 
  "POP ", 
  "PUSH2 0x13bd ", 
  "JUMP ", 
  "JUMPDEST ", 
  "PUSH1 0x40 ", 
  "MLOAD ", 
  "DUP1 ", 
  "DUP3 ", 
  "ISZERO ", 
  "ISZERO ", 
  "ISZERO ", 
  "ISZERO ", 
  "DUP2 ", 
  "MSTORE ", 
  "PUSH1 0x20 ", 
  "ADD ", 
  "SWAP2 ", 
  "POP ", 
  "POP ", 
  "PUSH1 0x40 ", 
  "MLOAD ", 
  "DUP1 ", 
  "SWAP2 ", 
  "SUB ", 
  "SWAP1 ", 
  "RETURN ", 
  "JUMPDEST ", 
  "CALLVALUE ", 
  "DUP1 ", 
  "ISZERO ", 
  "PUSH2 0x0726 ", 
  "JUMPI ", 
  "PUSH1 0x00 ", 
  "DUP1 ", 
  "REVERT ", 
  "JUMPDEST ", 
  "POP ", 
  "PUSH2 0x077b ", 
  "PUSH1 0x04 ", 
  "DUP1 ", 
  "CALLDATASIZE ", 
  "SUB ", 
  "DUP2 ", 
  "ADD ", 
  "SWAP1 ", 
  "DUP1 ", 
  "DUP1 ", 
  "CALLDATALOAD ", 
  "PUSH20 0xffffffffffffffffffffffffffffffffffffffff ", 
  "ISZERO ", 
  "AND ", 
  "SWAP1 ", 
  "PUSH1 0x20 ", 
  "ADD ", 
  "SWAP1 ", 
  "SWAP3 ", 
  "SWAP2 ", 
  "SWAP1 ", 
  "DUP1 ", 
  "CALLDATALOAD ", 
  "PUSH20 0xffffffffffffffffffffffffffffffffffffffff ", 
  "AND ", 
  "AND ", 
  "SWAP1 ", 
  "PUSH1 0x20 ", 
  "ADD ", 
  "SWAP1 ", 
  "SWAP3 ", 
  "SWAP2 ", 
  "SWAP1 ", 
  "POP ", 
  "POP ", 
  "POP ", 
  "PUSH2 0x1521 ", 
  "JUMP ", 
  "JUMPDEST ", 
  "PUSH1 0x40 ", 
  "MLOAD ", 
  "DUP1 ", 
  "DUP3 ", 
  "DUP2 ", 
  "MSTORE ", 
  "PUSH1 0x20 ", 
  "ADD ", 
  "SWAP2 ", 
  "POP ", 
  "POP ", 
  "PUSH1 0x40 ", 
  "MLOAD ", 
  "DUP1 ", 
  "SWAP2 ", 
  "SUB ", 
  "SWAP1 ", 
  "RETURN ", 
  "JUMPDEST ", 
  "CALLVALUE ", 
  "DUP1 ", 
  "ISZERO ", 
  "PUSH2 0x079d ", 
  "JUMPI ", 
  "PUSH1 0x00 ", 
  "DUP1 ", 
  "REVERT ", 
  "JUMPDEST ", 
  "POP ", 
  "PUSH2 0x07c6 ", 
  "PUSH1 0x04 ", 
  "DUP1 ", 
  "CALLDATASIZE ", 
  "SUB ", 
  "DUP2 ", 
  "ADD ", 
  "SWAP1 ", 
  "DUP1 ", 
  "DUP1 ", 
  "CALLDATALOAD ", 
  "SWAP1 ", 
  "PUSH1 0x20 ", 
  "ADD ", 
  "SWAP1 ", 
  "SWAP3 ", 
  "SWAP2 ", 
  "SWAP1 ", 
  "DUP1 ", 
  "CALLDATALOAD ", 
  "SWAP1 ", 
  "PUSH1 0x20 ", 
  "ADD ", 
  "SWAP1 ", 
  "SWAP3 ", 
  "SWAP2 ", 
  "SWAP1 ", 
  "POP ", 
  "POP ", 
  "POP ", 
  "PUSH2 0x15a8 ", 
  "JUMP ", 
  "JUMPDEST ", 
  "PUSH1 0x40 ", 
  "MLOAD ", 
  "DUP1 ", 
  "DUP3 ", 
  "DUP2 ", 
  "MSTORE ", 
  "PUSH1 0x20 ", 
  "ADD ", 
  "SWAP2 ", 
  "POP ", 
  "POP ", 
  "PUSH1 0x40 ", 
  "MLOAD ", 
  "DUP1 ", 
  "SWAP2 ", 
  "SUB ", 
  "SWAP1 ", 
  "RETURN ", 
  "JUMPDEST ", 
  "CALLVALUE ", 
  "DUP1 ", 
  "ISZERO ", 
  "PUSH2 0x07e8 ", 
  "JUMPI ", 
  "PUSH1 0x00 ", 
  "DUP1 ", 
  "REVERT ", 
  "JUMPDEST ", 
  "POP ", 
  "PUSH2 0x081d ", 
  "PUSH1 0x04 ", 
  "DUP1 ", 
  "CALLDATASIZE ", 
  "SUB ", 
  "DUP2 ", 
  "ADD ", 
  "SWAP1 ", 
  "DUP1 ", 
  "DUP1 ", 
  "CALLDATALOAD ", 
  "PUSH20 0xffffffffffffffffffffffffffffffffffffffff ", 
  "POP "
 ], 
 "overflow": false, 
 "money_concurrency": false, 
 "truncation": false
},"Owned-4":{
 "execution_paths": "12", 
 "callstack": false, 
 "reentrancy": false, 
 "modulo": false, 
 "division": false, 
 "execution_time": "0.836629152298", 
 "signedness": false, 
 "evm_code_coverage": "99.7", 
 "underflow": false, 
 "time_dependency": false, 
 "assertion_failure": false, 
 "timeout": false, 
 "dead_code": [
  "STOP "
 ], 
 "overflow": false, 
 "money_concurrency": false, 
 "truncation": false
},"SafeMath-4":{
 "execution_paths": "16", 
 "callstack": false, 
 "reentrancy": false, 
 "modulo": false, 
 "division": false, 
 "execution_time": "10.1808328629", 
 "signedness": false, 
 "evm_code_coverage": "99.8", 
 "underflow": false, 
 "time_dependency": false, 
 "assertion_failure": false, 
 "timeout": false, 
 "dead_code": [
  "STOP "
 ], 
 "overflow": false, 
 "money_concurrency": false, 
 "truncation": false
},"Hubscop-5":{
 "execution_paths": "65", 
 "callstack": false, 
 "reentrancy": false, 
 "modulo": false, 
 "division": false, 
 "execution_time": "50.0530800819", 
 "signedness": false, 
 "evm_code_coverage": "76.8", 
 "underflow": "\n./0x001fc4a7f2f586596308091c7b296d4535a25a90_ext.sol:Hubscop:103:16\n_totalSupply  - balances[address(0)]\n^", 
 "time_dependency": false, 
 "assertion_failure": false, 
 "timeout": true, 
 "dead_code": [
  "AND ", 
  "SWAP1 ", 
  "PUSH1 0x20 ", 
  "ADD ", 
  "SWAP1 ", 
  "SWAP3 ", 
  "SWAP2 ", 
  "SWAP1 ", 
  "POP ", 
  "POP ", 
  "POP ", 
  "PUSH2 0x15c4 ", 
  "JUMP ", 
  "JUMPDEST ", 
  "STOP ", 
  "JUMP ", 
  "REVERT ", 
  "JUMPDEST ", 
  "DUP1 ", 
  "POP ", 
  "PUSH1 0x01 ", 
  "DUP1 ", 
  "PUSH4 0xd05c78da ", 
  "EQ ", 
  "PUSH2 0x0613 ", 
  "JUMPI ", 
  "DUP1 ", 
  "PUSH4 0xd4ee1d90 ", 
  "EQ ", 
  "PUSH2 0x065e ", 
  "JUMPI ", 
  "DUP1 ", 
  "PUSH4 0xdc39d06d ", 
  "EQ ", 
  "PUSH2 0x06b5 ", 
  "JUMPI ", 
  "DUP1 ", 
  "PUSH4 0xdd62ed3e ", 
  "EQ ", 
  "PUSH2 0x071a ", 
  "JUMPI ", 
  "DUP1 ", 
  "PUSH4 0xe6cb9013 ", 
  "EQ ", 
  "PUSH2 0x0791 ", 
  "JUMPI ", 
  "DUP1 ", 
  "PUSH4 0xf2fde38b ", 
  "EQ ", 
  "PUSH2 0x07dc ", 
  "JUMPI ", 
  "EXP ", 
  "SWAP1 ", 
  "DUP2 ", 
  "SLOAD ", 
  "DUP2 ", 
  "PUSH20 0xffffffffffffffffffffffffffffffffffffffff ", 
  "JUMPDEST ", 
  "PUSH1 0x00 ", 
  "DUP2 ", 
  "DUP4 ", 
  "MUL ", 
  "SWAP1 ", 
  "POP ", 
  "PUSH1 0x00 ", 
  "DUP4 ", 
  "EQ ", 
  "DUP1 ", 
  "PUSH2 0x1386 ", 
  "JUMPI ", 
  "POP ", 
  "DUP2 ", 
  "DUP4 ", 
  "DUP3 ", 
  "DUP2 ", 
  "ISZERO ", 
  "ISZERO ", 
  "PUSH2 0x1383 ", 
  "JUMPI ", 
  "ASSERTFAIL ", 
  "JUMPDEST ", 
  "DIV ", 
  "EQ ", 
  "JUMPDEST ", 
  "ISZERO ", 
  "ISZERO ", 
  "PUSH2 0x1391 ", 
  "JUMPI ", 
  "PUSH1 0x00 ", 
  "DUP1 ", 
  "REVERT ", 
  "JUMPDEST ", 
  "SWAP3 ", 
  "SWAP2 ", 
  "POP ", 
  "POP ", 
  "JUMP ", 
  "JUMPDEST ", 
  "PUSH1 0x01 ", 
  "PUSH1 0x00 ", 
  "SWAP1 ", 
  "SLOAD ", 
  "SWAP1 ", 
  "PUSH2 0x0100 ", 
  "EXP ", 
  "SWAP1 ", 
  "DIV ", 
  "PUSH20 0xffffffffffffffffffffffffffffffffffffffff ", 
  "AND ", 
  "DUP2 ", 
  "JUMP ", 
  "JUMPDEST ", 
  "PUSH1 0x00 ", 
  "DUP1 ", 
  "PUSH1 0x00 ", 
  "SWAP1 ", 
  "SLOAD ", 
  "SWAP1 ", 
  "PUSH2 0x0100 ", 
  "EXP ", 
  "SWAP1 ", 
  "DIV ", 
  "PUSH20 0xffffffffffffffffffffffffffffffffffffffff ", 
  "AND ", 
  "PUSH20 0xffffffffffffffffffffffffffffffffffffffff ", 
  "AND ", 
  "CALLER ", 
  "PUSH20 0xffffffffffffffffffffffffffffffffffffffff ", 
  "AND ", 
  "EQ ", 
  "ISZERO ", 
  "ISZERO ", 
  "PUSH2 0x141a ", 
  "JUMPI ", 
  "PUSH1 0x00 ", 
  "DUP1 ", 
  "REVERT ", 
  "JUMPDEST ", 
  "DUP3 ", 
  "PUSH20 0xffffffffffffffffffffffffffffffffffffffff ", 
  "AND ", 
  "PUSH4 0xa9059cbb ", 
  "PUSH1 0x00 ", 
  "DUP1 ", 
  "SWAP1 ", 
  "SLOAD ", 
  "SWAP1 ", 
  "PUSH2 0x0100 ", 
  "EXP ", 
  "SWAP1 ", 
  "DIV ", 
  "PUSH20 0xffffffffffffffffffffffffffffffffffffffff ", 
  "AND ", 
  "DUP5 ", 
  "PUSH1 0x40 ", 
  "MLOAD ", 
  "DUP4 ", 
  "PUSH4 0xffffffff ", 
  "AND ", 
  "PUSH29 0x0100000000000000000000000000000000000000000000000000000000 ", 
  "AND ", 
  "EQ ", 
  "ISZERO ", 
  "MUL ", 
  "DUP2 ", 
  "MSTORE ", 
  "PUSH1 0x04 ", 
  "ADD ", 
  "DUP1 ", 
  "DUP4 ", 
  "PUSH20 0xffffffffffffffffffffffffffffffffffffffff ", 
  "PUSH2 0x161f ", 
  "AND ", 
  "JUMPI ", 
  "AND ", 
  "PUSH20 0xffffffffffffffffffffffffffffffffffffffff ", 
  "PUSH1 0x00 ", 
  "DUP1 ", 
  "SWAP1 ", 
  "AND ", 
  "DUP2 ", 
  "MSTORE ", 
  "PUSH1 0x20 ", 
  "ADD ", 
  "DUP3 ", 
  "DUP2 ", 
  "MSTORE ", 
  "PUSH1 0x20 ", 
  "ADD ", 
  "SWAP3 ", 
  "POP ", 
  "POP ", 
  "POP ", 
  "PUSH1 0x20 ", 
  "PUSH1 0x40 ", 
  "MLOAD ", 
  "DUP1 ", 
  "DUP4 ", 
  "SUB ", 
  "DUP2 ", 
  "PUSH1 0x00 ", 
  "DUP8 ", 
  "DUP1 ", 
  "EXTCODESIZE ", 
  "ISZERO ", 
  "DUP1 ", 
  "ISZERO ", 
  "PUSH2 0x14de ", 
  "JUMPI ", 
  "PUSH1 0x00 ", 
  "DUP1 ", 
  "REVERT ", 
  "JUMPDEST ", 
  "POP ", 
  "GAS ", 
  "CALL ", 
  "ISZERO ", 
  "DUP1 ", 
  "ISZERO ", 
  "PUSH2 0x14f2 ", 
  "JUMPI ", 
  "RETURNDATASIZE ", 
  "PUSH1 0x00 ", 
  "DUP1 ", 
  "RETURNDATACOPY ", 
  "RETURNDATASIZE ", 
  "PUSH1 0x00 ", 
  "REVERT ", 
  "JUMPDEST ", 
  "POP ", 
  "POP ", 
  "POP ", 
  "POP ", 
  "PUSH1 0x40 ", 
  "MLOAD ", 
  "RETURNDATASIZE ", 
  "PUSH1 0x20 ", 
  "DUP2 ", 
  "LT ", 
  "ISZERO ", 
  "PUSH2 0x1508 ", 
  "JUMPI ", 
  "PUSH1 0x00 ", 
  "DUP1 ", 
  "REVERT ", 
  "JUMPDEST ", 
  "DUP2 ", 
  "ADD ", 
  "SWAP1 ", 
  "DUP1 ", 
  "DUP1 ", 
  "MLOAD ", 
  "SWAP1 ", 
  "PUSH1 0x20 ", 
  "ADD ", 
  "SWAP1 ", 
  "SWAP3 ", 
  "SWAP2 ", 
  "SWAP1 ", 
  "POP ", 
  "POP ", 
  "POP ", 
  "SWAP1 ", 
  "POP ", 
  "SWAP3 ", 
  "SWAP2 ", 
  "POP ", 
  "POP ", 
  "JUMP ", 
  "JUMPDEST ", 
  "PUSH1 0x00 ", 
  "PUSH1 0x07 ", 
  "PUSH1 0x00 ", 
  "DUP5 ", 
  "PUSH20 0xffffffffffffffffffffffffffffffffffffffff ", 
  "AND ", 
  "PUSH20 0xffffffffffffffffffffffffffffffffffffffff ", 
  "AND ", 
  "DUP2 ", 
  "MSTORE ", 
  "PUSH1 0x20 ", 
  "ADD ", 
  "SWAP1 ", 
  "DUP2 ", 
  "MSTORE ", 
  "PUSH1 0x20 ", 
  "ADD ", 
  "PUSH1 0x00 ", 
  "SHA3 ", 
  "PUSH1 0x00 ", 
  "DUP4 ", 
  "PUSH20 0xffffffffffffffffffffffffffffffffffffffff ", 
  "PUSH1 0x00 ", 
  "DUP1 ", 
  "REVERT ", 
  "AND ", 
  "PUSH20 0xffffffffffffffffffffffffffffffffffffffff ", 
  "MUL ", 
  "MUL ", 
  "NOT ", 
  "AND ", 
  "DUP2 ", 
  "MSTORE ", 
  "PUSH1 0x20 ", 
  "ADD ", 
  "SWAP1 ", 
  "DUP2 ", 
  "MSTORE ", 
  "PUSH1 0x20 ", 
  "ADD ", 
  "PUSH1 0x00 ", 
  "SHA3 ", 
  "SLOAD ", 
  "SWAP1 ", 
  "POP ", 
  "SWAP3 ", 
  "SWAP2 ", 
  "POP ", 
  "POP ", 
  "JUMP ", 
  "JUMPDEST ", 
  "PUSH1 0x00 ", 
  "DUP1 ", 
  "SWAP1 ", 
  "SLOAD ", 
  "SWAP1 ", 
  "PUSH2 0x0100 ", 
  "EXP ", 
  "SWAP1 ", 
  "DIV ", 
  "PUSH20 0xffffffffffffffffffffffffffffffffffffffff ", 
  "AND ", 
  "PUSH20 0xffffffffffffffffffffffffffffffffffffffff ", 
  "AND ", 
  "CALLER ", 
  "PUSH20 0xffffffffffffffffffffffffffffffffffffffff ", 
  "JUMPDEST ", 
  "CALLVALUE ", 
  "DUP1 ", 
  "ISZERO ", 
  "PUSH2 0x061f ", 
  "JUMPI ", 
  "PUSH1 0x00 ", 
  "OR ", 
  "DUP1 ", 
  "REVERT ", 
  "JUMPDEST ", 
  "POP ", 
  "PUSH2 0x0648 ", 
  "PUSH1 0x00 ", 
  "PUSH1 0x04 ", 
  "PUSH2 0x0100 ", 
  "DUP1 ", 
  "CALLDATASIZE ", 
  "SUB ", 
  "DUP2 ", 
  "ADD ", 
  "SWAP1 ", 
  "DUP1 ", 
  "DUP1 ", 
  "CALLDATALOAD ", 
  "SWAP1 ", 
  "PUSH1 0x20 ", 
  "ADD ", 
  "SWAP1 ", 
  "SWAP3 ", 
  "SWAP2 ", 
  "SWAP1 ", 
  "DUP1 ", 
  "CALLDATALOAD ", 
  "SWAP1 ", 
  "PUSH1 0x20 ", 
  "SSTORE ", 
  "ADD ", 
  "SWAP1 ", 
  "SWAP3 ", 
  "SWAP2 ", 
  "SWAP1 ", 
  "POP ", 
  "POP ", 
  "POP ", 
  "PUSH2 0x1366 ", 
  "DUP4 ", 
  "PUSH20 0xffffffffffffffffffffffffffffffffffffffff ", 
  "JUMP ", 
  "JUMPDEST ", 
  "PUSH1 0x40 ", 
  "MLOAD ", 
  "DUP1 ", 
  "DUP3 ", 
  "DUP2 ", 
  "MSTORE ", 
  "PUSH1 0x20 ", 
  "ADD ", 
  "SWAP2 ", 
  "POP ", 
  "POP ", 
  "PUSH1 0x40 ", 
  "MLOAD ", 
  "DUP1 ", 
  "SWAP2 ", 
  "SUB ", 
  "SWAP1 ", 
  "RETURN ", 
  "JUMPDEST ", 
  "CALLVALUE ", 
  "DUP1 ", 
  "ISZERO ", 
  "PUSH2 0x066a ", 
  "STOP ", 
  "JUMPI ", 
  "PUSH1 0x00 ", 
  "DUP1 ", 
  "REVERT ", 
  "JUMPDEST ", 
  "POP ", 
  "PUSH2 0x0673 ", 
  "PUSH2 0x1397 ", 
  "JUMP ", 
  "JUMPDEST ", 
  "PUSH1 0x40 ", 
  "MLOAD ", 
  "DUP1 ", 
  "DUP3 ", 
  "PUSH20 0xffffffffffffffffffffffffffffffffffffffff ", 
  "AND ", 
  "PUSH20 0xffffffffffffffffffffffffffffffffffffffff ", 
  "AND ", 
  "DUP2 ", 
  "MSTORE ", 
  "PUSH1 0x20 ", 
  "ADD ", 
  "SWAP2 ", 
  "POP ", 
  "POP ", 
  "PUSH1 0x40 ", 
  "MLOAD ", 
  "DUP1 ", 
  "SWAP2 ", 
  "SUB ", 
  "SWAP1 ", 
  "RETURN ", 
  "JUMPDEST ", 
  "CALLVALUE ", 
  "DUP1 ", 
  "ISZERO ", 
  "PUSH2 0x06c1 ", 
  "JUMPI ", 
  "PUSH1 0x00 ", 
  "DUP1 ", 
  "REVERT ", 
  "JUMPDEST ", 
  "POP ", 
  "PUSH2 0x0700 ", 
  "PUSH1 0x04 ", 
  "DUP1 ", 
  "CALLDATASIZE ", 
  "SUB ", 
  "DUP2 ", 
  "ADD ", 
  "SWAP1 ", 
  "DUP1 ", 
  "DUP1 ", 
  "CALLDATALOAD ", 
  "PUSH20 0xffffffffffffffffffffffffffffffffffffffff ", 
  "AND ", 
  "SWAP1 ", 
  "PUSH1 0x20 ", 
  "ADD ", 
  "SWAP1 ", 
  "SWAP3 ", 
  "SWAP2 ", 
  "SWAP1 ", 
  "DUP1 ", 
  "CALLDATALOAD ", 
  "SWAP1 ", 
  "PUSH1 0x20 ", 
  "ADD ", 
  "SWAP1 ", 
  "SWAP3 ", 
  "SWAP2 ", 
  "SWAP1 ", 
  "POP ", 
  "POP ", 
  "POP ", 
  "PUSH2 0x13bd ", 
  "JUMP ", 
  "JUMPDEST ", 
  "PUSH1 0x40 ", 
  "MLOAD ", 
  "DUP1 ", 
  "DUP3 ", 
  "ISZERO ", 
  "ISZERO ", 
  "ISZERO ", 
  "ISZERO ", 
  "DUP2 ", 
  "MSTORE ", 
  "PUSH1 0x20 ", 
  "ADD ", 
  "SWAP2 ", 
  "POP ", 
  "POP ", 
  "PUSH1 0x40 ", 
  "MLOAD ", 
  "DUP1 ", 
  "SWAP2 ", 
  "SUB ", 
  "SWAP1 ", 
  "RETURN ", 
  "JUMPDEST ", 
  "CALLVALUE ", 
  "DUP1 ", 
  "ISZERO ", 
  "PUSH2 0x0726 ", 
  "JUMPI ", 
  "PUSH1 0x00 ", 
  "DUP1 ", 
  "REVERT ", 
  "JUMPDEST ", 
  "POP ", 
  "PUSH2 0x077b ", 
  "PUSH1 0x04 ", 
  "DUP1 ", 
  "CALLDATASIZE ", 
  "SUB ", 
  "DUP2 ", 
  "ADD ", 
  "SWAP1 ", 
  "DUP1 ", 
  "DUP1 ", 
  "CALLDATALOAD ", 
  "PUSH20 0xffffffffffffffffffffffffffffffffffffffff ", 
  "ISZERO ", 
  "AND ", 
  "SWAP1 ", 
  "PUSH1 0x20 ", 
  "ADD ", 
  "SWAP1 ", 
  "SWAP3 ", 
  "SWAP2 ", 
  "SWAP1 ", 
  "DUP1 ", 
  "CALLDATALOAD ", 
  "PUSH20 0xffffffffffffffffffffffffffffffffffffffff ", 
  "AND ", 
  "AND ", 
  "SWAP1 ", 
  "PUSH1 0x20 ", 
  "ADD ", 
  "SWAP1 ", 
  "SWAP3 ", 
  "SWAP2 ", 
  "SWAP1 ", 
  "POP ", 
  "POP ", 
  "POP ", 
  "PUSH2 0x1521 ", 
  "JUMP ", 
  "JUMPDEST ", 
  "PUSH1 0x40 ", 
  "MLOAD ", 
  "DUP1 ", 
  "DUP3 ", 
  "DUP2 ", 
  "MSTORE ", 
  "PUSH1 0x20 ", 
  "ADD ", 
  "SWAP2 ", 
  "POP ", 
  "POP ", 
  "PUSH1 0x40 ", 
  "MLOAD ", 
  "DUP1 ", 
  "SWAP2 ", 
  "SUB ", 
  "SWAP1 ", 
  "RETURN ", 
  "JUMPDEST ", 
  "CALLVALUE ", 
  "DUP1 ", 
  "ISZERO ", 
  "PUSH2 0x079d ", 
  "JUMPI ", 
  "PUSH1 0x00 ", 
  "DUP1 ", 
  "REVERT ", 
  "JUMPDEST ", 
  "POP ", 
  "PUSH2 0x07c6 ", 
  "PUSH1 0x04 ", 
  "DUP1 ", 
  "CALLDATASIZE ", 
  "SUB ", 
  "DUP2 ", 
  "ADD ", 
  "SWAP1 ", 
  "DUP1 ", 
  "DUP1 ", 
  "CALLDATALOAD ", 
  "SWAP1 ", 
  "PUSH1 0x20 ", 
  "ADD ", 
  "SWAP1 ", 
  "SWAP3 ", 
  "SWAP2 ", 
  "SWAP1 ", 
  "DUP1 ", 
  "CALLDATALOAD ", 
  "SWAP1 ", 
  "PUSH1 0x20 ", 
  "ADD ", 
  "SWAP1 ", 
  "SWAP3 ", 
  "SWAP2 ", 
  "SWAP1 ", 
  "POP ", 
  "POP ", 
  "POP ", 
  "PUSH2 0x15a8 ", 
  "JUMP ", 
  "JUMPDEST ", 
  "PUSH1 0x40 ", 
  "MLOAD ", 
  "DUP1 ", 
  "DUP3 ", 
  "DUP2 ", 
  "MSTORE ", 
  "PUSH1 0x20 ", 
  "ADD ", 
  "SWAP2 ", 
  "POP ", 
  "POP ", 
  "PUSH1 0x40 ", 
  "MLOAD ", 
  "DUP1 ", 
  "SWAP2 ", 
  "SUB ", 
  "SWAP1 ", 
  "RETURN ", 
  "JUMPDEST ", 
  "CALLVALUE ", 
  "DUP1 ", 
  "ISZERO ", 
  "PUSH2 0x07e8 ", 
  "JUMPI ", 
  "PUSH1 0x00 ", 
  "DUP1 ", 
  "REVERT ", 
  "JUMPDEST ", 
  "POP ", 
  "PUSH2 0x081d ", 
  "PUSH1 0x04 ", 
  "DUP1 ", 
  "CALLDATASIZE ", 
  "SUB ", 
  "DUP2 ", 
  "ADD ", 
  "SWAP1 ", 
  "DUP1 ", 
  "DUP1 ", 
  "CALLDATALOAD ", 
  "PUSH20 0xffffffffffffffffffffffffffffffffffffffff ", 
  "POP "
 ], 
 "overflow": false, 
 "money_concurrency": false, 
 "truncation": false
},"Owned-5":{
 "execution_paths": "12", 
 "callstack": false, 
 "reentrancy": false, 
 "modulo": false, 
 "division": false, 
 "execution_time": "0.640722990036", 
 "signedness": false, 
 "evm_code_coverage": "99.7", 
 "underflow": false, 
 "time_dependency": false, 
 "assertion_failure": false, 
 "timeout": false, 
 "dead_code": [
  "STOP "
 ], 
 "overflow": false, 
 "money_concurrency": false, 
 "truncation": false
},"SafeMath-5":{
 "execution_paths": "16", 
 "callstack": false, 
 "reentrancy": false, 
 "modulo": false, 
 "division": false, 
 "execution_time": "9.37615084648", 
 "signedness": false, 
 "evm_code_coverage": "99.8", 
 "underflow": false, 
 "time_dependency": false, 
 "assertion_failure": false, 
 "timeout": false, 
 "dead_code": [
  "STOP "
 ], 
 "overflow": false, 
 "money_concurrency": false, 
 "truncation": false
},"Hubscop-6":{
 "execution_paths": "62", 
 "callstack": false, 
 "reentrancy": false, 
 "modulo": false, 
 "division": false, 
 "execution_time": "50.0575139523", 
 "signedness": false, 
 "evm_code_coverage": "76.8", 
 "underflow": "\n./0x001fc4a7f2f586596308091c7b296d4535a25a90_ext.sol:Hubscop:103:16\n_totalSupply  - balances[address(0)]\n^", 
 "time_dependency": false, 
 "assertion_failure": false, 
 "timeout": true, 
 "dead_code": [
  "AND ", 
  "SWAP1 ", 
  "PUSH1 0x20 ", 
  "ADD ", 
  "SWAP1 ", 
  "SWAP3 ", 
  "SWAP2 ", 
  "SWAP1 ", 
  "POP ", 
  "POP ", 
  "POP ", 
  "PUSH2 0x15c4 ", 
  "JUMP ", 
  "JUMPDEST ", 
  "STOP ", 
  "JUMP ", 
  "REVERT ", 
  "JUMPDEST ", 
  "DUP1 ", 
  "POP ", 
  "PUSH1 0x01 ", 
  "DUP1 ", 
  "PUSH4 0xd05c78da ", 
  "EQ ", 
  "PUSH2 0x0613 ", 
  "JUMPI ", 
  "DUP1 ", 
  "PUSH4 0xd4ee1d90 ", 
  "EQ ", 
  "PUSH2 0x065e ", 
  "JUMPI ", 
  "DUP1 ", 
  "PUSH4 0xdc39d06d ", 
  "EQ ", 
  "PUSH2 0x06b5 ", 
  "JUMPI ", 
  "DUP1 ", 
  "PUSH4 0xdd62ed3e ", 
  "EQ ", 
  "PUSH2 0x071a ", 
  "JUMPI ", 
  "DUP1 ", 
  "PUSH4 0xe6cb9013 ", 
  "EQ ", 
  "PUSH2 0x0791 ", 
  "JUMPI ", 
  "DUP1 ", 
  "PUSH4 0xf2fde38b ", 
  "EQ ", 
  "PUSH2 0x07dc ", 
  "JUMPI ", 
  "EXP ", 
  "SWAP1 ", 
  "DUP2 ", 
  "SLOAD ", 
  "DUP2 ", 
  "PUSH20 0xffffffffffffffffffffffffffffffffffffffff ", 
  "JUMPDEST ", 
  "PUSH1 0x00 ", 
  "DUP2 ", 
  "DUP4 ", 
  "MUL ", 
  "SWAP1 ", 
  "POP ", 
  "PUSH1 0x00 ", 
  "DUP4 ", 
  "EQ ", 
  "DUP1 ", 
  "PUSH2 0x1386 ", 
  "JUMPI ", 
  "POP ", 
  "DUP2 ", 
  "DUP4 ", 
  "DUP3 ", 
  "DUP2 ", 
  "ISZERO ", 
  "ISZERO ", 
  "PUSH2 0x1383 ", 
  "JUMPI ", 
  "ASSERTFAIL ", 
  "JUMPDEST ", 
  "DIV ", 
  "EQ ", 
  "JUMPDEST ", 
  "ISZERO ", 
  "ISZERO ", 
  "PUSH2 0x1391 ", 
  "JUMPI ", 
  "PUSH1 0x00 ", 
  "DUP1 ", 
  "REVERT ", 
  "JUMPDEST ", 
  "SWAP3 ", 
  "SWAP2 ", 
  "POP ", 
  "POP ", 
  "JUMP ", 
  "JUMPDEST ", 
  "PUSH1 0x01 ", 
  "PUSH1 0x00 ", 
  "SWAP1 ", 
  "SLOAD ", 
  "SWAP1 ", 
  "PUSH2 0x0100 ", 
  "EXP ", 
  "SWAP1 ", 
  "DIV ", 
  "PUSH20 0xffffffffffffffffffffffffffffffffffffffff ", 
  "AND ", 
  "DUP2 ", 
  "JUMP ", 
  "JUMPDEST ", 
  "PUSH1 0x00 ", 
  "DUP1 ", 
  "PUSH1 0x00 ", 
  "SWAP1 ", 
  "SLOAD ", 
  "SWAP1 ", 
  "PUSH2 0x0100 ", 
  "EXP ", 
  "SWAP1 ", 
  "DIV ", 
  "PUSH20 0xffffffffffffffffffffffffffffffffffffffff ", 
  "AND ", 
  "PUSH20 0xffffffffffffffffffffffffffffffffffffffff ", 
  "AND ", 
  "CALLER ", 
  "PUSH20 0xffffffffffffffffffffffffffffffffffffffff ", 
  "AND ", 
  "EQ ", 
  "ISZERO ", 
  "ISZERO ", 
  "PUSH2 0x141a ", 
  "JUMPI ", 
  "PUSH1 0x00 ", 
  "DUP1 ", 
  "REVERT ", 
  "JUMPDEST ", 
  "DUP3 ", 
  "PUSH20 0xffffffffffffffffffffffffffffffffffffffff ", 
  "AND ", 
  "PUSH4 0xa9059cbb ", 
  "PUSH1 0x00 ", 
  "DUP1 ", 
  "SWAP1 ", 
  "SLOAD ", 
  "SWAP1 ", 
  "PUSH2 0x0100 ", 
  "EXP ", 
  "SWAP1 ", 
  "DIV ", 
  "PUSH20 0xffffffffffffffffffffffffffffffffffffffff ", 
  "AND ", 
  "DUP5 ", 
  "PUSH1 0x40 ", 
  "MLOAD ", 
  "DUP4 ", 
  "PUSH4 0xffffffff ", 
  "AND ", 
  "PUSH29 0x0100000000000000000000000000000000000000000000000000000000 ", 
  "AND ", 
  "EQ ", 
  "ISZERO ", 
  "MUL ", 
  "DUP2 ", 
  "MSTORE ", 
  "PUSH1 0x04 ", 
  "ADD ", 
  "DUP1 ", 
  "DUP4 ", 
  "PUSH20 0xffffffffffffffffffffffffffffffffffffffff ", 
  "PUSH2 0x161f ", 
  "AND ", 
  "JUMPI ", 
  "AND ", 
  "PUSH20 0xffffffffffffffffffffffffffffffffffffffff ", 
  "PUSH1 0x00 ", 
  "DUP1 ", 
  "SWAP1 ", 
  "AND ", 
  "DUP2 ", 
  "MSTORE ", 
  "PUSH1 0x20 ", 
  "ADD ", 
  "DUP3 ", 
  "DUP2 ", 
  "MSTORE ", 
  "PUSH1 0x20 ", 
  "ADD ", 
  "SWAP3 ", 
  "POP ", 
  "POP ", 
  "POP ", 
  "PUSH1 0x20 ", 
  "PUSH1 0x40 ", 
  "MLOAD ", 
  "DUP1 ", 
  "DUP4 ", 
  "SUB ", 
  "DUP2 ", 
  "PUSH1 0x00 ", 
  "DUP8 ", 
  "DUP1 ", 
  "EXTCODESIZE ", 
  "ISZERO ", 
  "DUP1 ", 
  "ISZERO ", 
  "PUSH2 0x14de ", 
  "JUMPI ", 
  "PUSH1 0x00 ", 
  "DUP1 ", 
  "REVERT ", 
  "JUMPDEST ", 
  "POP ", 
  "GAS ", 
  "CALL ", 
  "ISZERO ", 
  "DUP1 ", 
  "ISZERO ", 
  "PUSH2 0x14f2 ", 
  "JUMPI ", 
  "RETURNDATASIZE ", 
  "PUSH1 0x00 ", 
  "DUP1 ", 
  "RETURNDATACOPY ", 
  "RETURNDATASIZE ", 
  "PUSH1 0x00 ", 
  "REVERT ", 
  "JUMPDEST ", 
  "POP ", 
  "POP ", 
  "POP ", 
  "POP ", 
  "PUSH1 0x40 ", 
  "MLOAD ", 
  "RETURNDATASIZE ", 
  "PUSH1 0x20 ", 
  "DUP2 ", 
  "LT ", 
  "ISZERO ", 
  "PUSH2 0x1508 ", 
  "JUMPI ", 
  "PUSH1 0x00 ", 
  "DUP1 ", 
  "REVERT ", 
  "JUMPDEST ", 
  "DUP2 ", 
  "ADD ", 
  "SWAP1 ", 
  "DUP1 ", 
  "DUP1 ", 
  "MLOAD ", 
  "SWAP1 ", 
  "PUSH1 0x20 ", 
  "ADD ", 
  "SWAP1 ", 
  "SWAP3 ", 
  "SWAP2 ", 
  "SWAP1 ", 
  "POP ", 
  "POP ", 
  "POP ", 
  "SWAP1 ", 
  "POP ", 
  "SWAP3 ", 
  "SWAP2 ", 
  "POP ", 
  "POP ", 
  "JUMP ", 
  "JUMPDEST ", 
  "PUSH1 0x00 ", 
  "PUSH1 0x07 ", 
  "PUSH1 0x00 ", 
  "DUP5 ", 
  "PUSH20 0xffffffffffffffffffffffffffffffffffffffff ", 
  "AND ", 
  "PUSH20 0xffffffffffffffffffffffffffffffffffffffff ", 
  "AND ", 
  "DUP2 ", 
  "MSTORE ", 
  "PUSH1 0x20 ", 
  "ADD ", 
  "SWAP1 ", 
  "DUP2 ", 
  "MSTORE ", 
  "PUSH1 0x20 ", 
  "ADD ", 
  "PUSH1 0x00 ", 
  "SHA3 ", 
  "PUSH1 0x00 ", 
  "DUP4 ", 
  "PUSH20 0xffffffffffffffffffffffffffffffffffffffff ", 
  "PUSH1 0x00 ", 
  "DUP1 ", 
  "REVERT ", 
  "AND ", 
  "PUSH20 0xffffffffffffffffffffffffffffffffffffffff ", 
  "MUL ", 
  "MUL ", 
  "NOT ", 
  "AND ", 
  "DUP2 ", 
  "MSTORE ", 
  "PUSH1 0x20 ", 
  "ADD ", 
  "SWAP1 ", 
  "DUP2 ", 
  "MSTORE ", 
  "PUSH1 0x20 ", 
  "ADD ", 
  "PUSH1 0x00 ", 
  "SHA3 ", 
  "SLOAD ", 
  "SWAP1 ", 
  "POP ", 
  "SWAP3 ", 
  "SWAP2 ", 
  "POP ", 
  "POP ", 
  "JUMP ", 
  "JUMPDEST ", 
  "PUSH1 0x00 ", 
  "DUP1 ", 
  "SWAP1 ", 
  "SLOAD ", 
  "SWAP1 ", 
  "PUSH2 0x0100 ", 
  "EXP ", 
  "SWAP1 ", 
  "DIV ", 
  "PUSH20 0xffffffffffffffffffffffffffffffffffffffff ", 
  "AND ", 
  "PUSH20 0xffffffffffffffffffffffffffffffffffffffff ", 
  "AND ", 
  "CALLER ", 
  "PUSH20 0xffffffffffffffffffffffffffffffffffffffff ", 
  "JUMPDEST ", 
  "CALLVALUE ", 
  "DUP1 ", 
  "ISZERO ", 
  "PUSH2 0x061f ", 
  "JUMPI ", 
  "PUSH1 0x00 ", 
  "OR ", 
  "DUP1 ", 
  "REVERT ", 
  "JUMPDEST ", 
  "POP ", 
  "PUSH2 0x0648 ", 
  "PUSH1 0x00 ", 
  "PUSH1 0x04 ", 
  "PUSH2 0x0100 ", 
  "DUP1 ", 
  "CALLDATASIZE ", 
  "SUB ", 
  "DUP2 ", 
  "ADD ", 
  "SWAP1 ", 
  "DUP1 ", 
  "DUP1 ", 
  "CALLDATALOAD ", 
  "SWAP1 ", 
  "PUSH1 0x20 ", 
  "ADD ", 
  "SWAP1 ", 
  "SWAP3 ", 
  "SWAP2 ", 
  "SWAP1 ", 
  "DUP1 ", 
  "CALLDATALOAD ", 
  "SWAP1 ", 
  "PUSH1 0x20 ", 
  "SSTORE ", 
  "ADD ", 
  "SWAP1 ", 
  "SWAP3 ", 
  "SWAP2 ", 
  "SWAP1 ", 
  "POP ", 
  "POP ", 
  "POP ", 
  "PUSH2 0x1366 ", 
  "DUP4 ", 
  "PUSH20 0xffffffffffffffffffffffffffffffffffffffff ", 
  "JUMP ", 
  "JUMPDEST ", 
  "PUSH1 0x40 ", 
  "MLOAD ", 
  "DUP1 ", 
  "DUP3 ", 
  "DUP2 ", 
  "MSTORE ", 
  "PUSH1 0x20 ", 
  "ADD ", 
  "SWAP2 ", 
  "POP ", 
  "POP ", 
  "PUSH1 0x40 ", 
  "MLOAD ", 
  "DUP1 ", 
  "SWAP2 ", 
  "SUB ", 
  "SWAP1 ", 
  "RETURN ", 
  "JUMPDEST ", 
  "CALLVALUE ", 
  "DUP1 ", 
  "ISZERO ", 
  "PUSH2 0x066a ", 
  "STOP ", 
  "JUMPI ", 
  "PUSH1 0x00 ", 
  "DUP1 ", 
  "REVERT ", 
  "JUMPDEST ", 
  "POP ", 
  "PUSH2 0x0673 ", 
  "PUSH2 0x1397 ", 
  "JUMP ", 
  "JUMPDEST ", 
  "PUSH1 0x40 ", 
  "MLOAD ", 
  "DUP1 ", 
  "DUP3 ", 
  "PUSH20 0xffffffffffffffffffffffffffffffffffffffff ", 
  "AND ", 
  "PUSH20 0xffffffffffffffffffffffffffffffffffffffff ", 
  "AND ", 
  "DUP2 ", 
  "MSTORE ", 
  "PUSH1 0x20 ", 
  "ADD ", 
  "SWAP2 ", 
  "POP ", 
  "POP ", 
  "PUSH1 0x40 ", 
  "MLOAD ", 
  "DUP1 ", 
  "SWAP2 ", 
  "SUB ", 
  "SWAP1 ", 
  "RETURN ", 
  "JUMPDEST ", 
  "CALLVALUE ", 
  "DUP1 ", 
  "ISZERO ", 
  "PUSH2 0x06c1 ", 
  "JUMPI ", 
  "PUSH1 0x00 ", 
  "DUP1 ", 
  "REVERT ", 
  "JUMPDEST ", 
  "POP ", 
  "PUSH2 0x0700 ", 
  "PUSH1 0x04 ", 
  "DUP1 ", 
  "CALLDATASIZE ", 
  "SUB ", 
  "DUP2 ", 
  "ADD ", 
  "SWAP1 ", 
  "DUP1 ", 
  "DUP1 ", 
  "CALLDATALOAD ", 
  "PUSH20 0xffffffffffffffffffffffffffffffffffffffff ", 
  "AND ", 
  "SWAP1 ", 
  "PUSH1 0x20 ", 
  "ADD ", 
  "SWAP1 ", 
  "SWAP3 ", 
  "SWAP2 ", 
  "SWAP1 ", 
  "DUP1 ", 
  "CALLDATALOAD ", 
  "SWAP1 ", 
  "PUSH1 0x20 ", 
  "ADD ", 
  "SWAP1 ", 
  "SWAP3 ", 
  "SWAP2 ", 
  "SWAP1 ", 
  "POP ", 
  "POP ", 
  "POP ", 
  "PUSH2 0x13bd ", 
  "JUMP ", 
  "JUMPDEST ", 
  "PUSH1 0x40 ", 
  "MLOAD ", 
  "DUP1 ", 
  "DUP3 ", 
  "ISZERO ", 
  "ISZERO ", 
  "ISZERO ", 
  "ISZERO ", 
  "DUP2 ", 
  "MSTORE ", 
  "PUSH1 0x20 ", 
  "ADD ", 
  "SWAP2 ", 
  "POP ", 
  "POP ", 
  "PUSH1 0x40 ", 
  "MLOAD ", 
  "DUP1 ", 
  "SWAP2 ", 
  "SUB ", 
  "SWAP1 ", 
  "RETURN ", 
  "JUMPDEST ", 
  "CALLVALUE ", 
  "DUP1 ", 
  "ISZERO ", 
  "PUSH2 0x0726 ", 
  "JUMPI ", 
  "PUSH1 0x00 ", 
  "DUP1 ", 
  "REVERT ", 
  "JUMPDEST ", 
  "POP ", 
  "PUSH2 0x077b ", 
  "PUSH1 0x04 ", 
  "DUP1 ", 
  "CALLDATASIZE ", 
  "SUB ", 
  "DUP2 ", 
  "ADD ", 
  "SWAP1 ", 
  "DUP1 ", 
  "DUP1 ", 
  "CALLDATALOAD ", 
  "PUSH20 0xffffffffffffffffffffffffffffffffffffffff ", 
  "ISZERO ", 
  "AND ", 
  "SWAP1 ", 
  "PUSH1 0x20 ", 
  "ADD ", 
  "SWAP1 ", 
  "SWAP3 ", 
  "SWAP2 ", 
  "SWAP1 ", 
  "DUP1 ", 
  "CALLDATALOAD ", 
  "PUSH20 0xffffffffffffffffffffffffffffffffffffffff ", 
  "AND ", 
  "AND ", 
  "SWAP1 ", 
  "PUSH1 0x20 ", 
  "ADD ", 
  "SWAP1 ", 
  "SWAP3 ", 
  "SWAP2 ", 
  "SWAP1 ", 
  "POP ", 
  "POP ", 
  "POP ", 
  "PUSH2 0x1521 ", 
  "JUMP ", 
  "JUMPDEST ", 
  "PUSH1 0x40 ", 
  "MLOAD ", 
  "DUP1 ", 
  "DUP3 ", 
  "DUP2 ", 
  "MSTORE ", 
  "PUSH1 0x20 ", 
  "ADD ", 
  "SWAP2 ", 
  "POP ", 
  "POP ", 
  "PUSH1 0x40 ", 
  "MLOAD ", 
  "DUP1 ", 
  "SWAP2 ", 
  "SUB ", 
  "SWAP1 ", 
  "RETURN ", 
  "JUMPDEST ", 
  "CALLVALUE ", 
  "DUP1 ", 
  "ISZERO ", 
  "PUSH2 0x079d ", 
  "JUMPI ", 
  "PUSH1 0x00 ", 
  "DUP1 ", 
  "REVERT ", 
  "JUMPDEST ", 
  "POP ", 
  "PUSH2 0x07c6 ", 
  "PUSH1 0x04 ", 
  "DUP1 ", 
  "CALLDATASIZE ", 
  "SUB ", 
  "DUP2 ", 
  "ADD ", 
  "SWAP1 ", 
  "DUP1 ", 
  "DUP1 ", 
  "CALLDATALOAD ", 
  "SWAP1 ", 
  "PUSH1 0x20 ", 
  "ADD ", 
  "SWAP1 ", 
  "SWAP3 ", 
  "SWAP2 ", 
  "SWAP1 ", 
  "DUP1 ", 
  "CALLDATALOAD ", 
  "SWAP1 ", 
  "PUSH1 0x20 ", 
  "ADD ", 
  "SWAP1 ", 
  "SWAP3 ", 
  "SWAP2 ", 
  "SWAP1 ", 
  "POP ", 
  "POP ", 
  "POP ", 
  "PUSH2 0x15a8 ", 
  "JUMP ", 
  "JUMPDEST ", 
  "PUSH1 0x40 ", 
  "MLOAD ", 
  "DUP1 ", 
  "DUP3 ", 
  "DUP2 ", 
  "MSTORE ", 
  "PUSH1 0x20 ", 
  "ADD ", 
  "SWAP2 ", 
  "POP ", 
  "POP ", 
  "PUSH1 0x40 ", 
  "MLOAD ", 
  "DUP1 ", 
  "SWAP2 ", 
  "SUB ", 
  "SWAP1 ", 
  "RETURN ", 
  "JUMPDEST ", 
  "CALLVALUE ", 
  "DUP1 ", 
  "ISZERO ", 
  "PUSH2 0x07e8 ", 
  "JUMPI ", 
  "PUSH1 0x00 ", 
  "DUP1 ", 
  "REVERT ", 
  "JUMPDEST ", 
  "POP ", 
  "PUSH2 0x081d ", 
  "PUSH1 0x04 ", 
  "DUP1 ", 
  "CALLDATASIZE ", 
  "SUB ", 
  "DUP2 ", 
  "ADD ", 
  "SWAP1 ", 
  "DUP1 ", 
  "DUP1 ", 
  "CALLDATALOAD ", 
  "PUSH20 0xffffffffffffffffffffffffffffffffffffffff ", 
  "POP "
 ], 
 "overflow": false, 
 "money_concurrency": false, 
 "truncation": false
},"Owned-6":{
 "execution_paths": "12", 
 "callstack": false, 
 "reentrancy": false, 
 "modulo": false, 
 "division": false, 
 "execution_time": "0.811863183975", 
 "signedness": false, 
 "evm_code_coverage": "99.7", 
 "underflow": false, 
 "time_dependency": false, 
 "assertion_failure": false, 
 "timeout": false, 
 "dead_code": [
  "STOP "
 ], 
 "overflow": false, 
 "money_concurrency": false, 
 "truncation": false
},"SafeMath-6":{
 "execution_paths": "16", 
 "callstack": false, 
 "reentrancy": false, 
 "modulo": false, 
 "division": false, 
 "execution_time": "10.1079070568", 
 "signedness": false, 
 "evm_code_coverage": "99.8", 
 "underflow": false, 
 "time_dependency": false, 
 "assertion_failure": false, 
 "timeout": false, 
 "dead_code": [
  "STOP "
 ], 
 "overflow": false, 
 "money_concurrency": false, 
 "truncation": false
},"Hubscop-7":{
 "execution_paths": "65", 
 "callstack": false, 
 "reentrancy": false, 
 "modulo": false, 
 "division": false, 
 "execution_time": "50.1117179394", 
 "signedness": false, 
 "evm_code_coverage": "76.8", 
 "underflow": "\n./0x001fc4a7f2f586596308091c7b296d4535a25a90_ext.sol:Hubscop:103:16\n_totalSupply  - balances[address(0)]\n^", 
 "time_dependency": false, 
 "assertion_failure": false, 
 "timeout": true, 
 "dead_code": [
  "AND ", 
  "SWAP1 ", 
  "PUSH1 0x20 ", 
  "ADD ", 
  "SWAP1 ", 
  "SWAP3 ", 
  "SWAP2 ", 
  "SWAP1 ", 
  "POP ", 
  "POP ", 
  "POP ", 
  "PUSH2 0x15c4 ", 
  "JUMP ", 
  "JUMPDEST ", 
  "STOP ", 
  "JUMP ", 
  "REVERT ", 
  "JUMPDEST ", 
  "DUP1 ", 
  "POP ", 
  "PUSH1 0x01 ", 
  "DUP1 ", 
  "PUSH4 0xd05c78da ", 
  "EQ ", 
  "PUSH2 0x0613 ", 
  "JUMPI ", 
  "DUP1 ", 
  "PUSH4 0xd4ee1d90 ", 
  "EQ ", 
  "PUSH2 0x065e ", 
  "JUMPI ", 
  "DUP1 ", 
  "PUSH4 0xdc39d06d ", 
  "EQ ", 
  "PUSH2 0x06b5 ", 
  "JUMPI ", 
  "DUP1 ", 
  "PUSH4 0xdd62ed3e ", 
  "EQ ", 
  "PUSH2 0x071a ", 
  "JUMPI ", 
  "DUP1 ", 
  "PUSH4 0xe6cb9013 ", 
  "EQ ", 
  "PUSH2 0x0791 ", 
  "JUMPI ", 
  "DUP1 ", 
  "PUSH4 0xf2fde38b ", 
  "EQ ", 
  "PUSH2 0x07dc ", 
  "JUMPI ", 
  "EXP ", 
  "SWAP1 ", 
  "DUP2 ", 
  "SLOAD ", 
  "DUP2 ", 
  "PUSH20 0xffffffffffffffffffffffffffffffffffffffff ", 
  "JUMPDEST ", 
  "PUSH1 0x00 ", 
  "DUP2 ", 
  "DUP4 ", 
  "MUL ", 
  "SWAP1 ", 
  "POP ", 
  "PUSH1 0x00 ", 
  "DUP4 ", 
  "EQ ", 
  "DUP1 ", 
  "PUSH2 0x1386 ", 
  "JUMPI ", 
  "POP ", 
  "DUP2 ", 
  "DUP4 ", 
  "DUP3 ", 
  "DUP2 ", 
  "ISZERO ", 
  "ISZERO ", 
  "PUSH2 0x1383 ", 
  "JUMPI ", 
  "ASSERTFAIL ", 
  "JUMPDEST ", 
  "DIV ", 
  "EQ ", 
  "JUMPDEST ", 
  "ISZERO ", 
  "ISZERO ", 
  "PUSH2 0x1391 ", 
  "JUMPI ", 
  "PUSH1 0x00 ", 
  "DUP1 ", 
  "REVERT ", 
  "JUMPDEST ", 
  "SWAP3 ", 
  "SWAP2 ", 
  "POP ", 
  "POP ", 
  "JUMP ", 
  "JUMPDEST ", 
  "PUSH1 0x01 ", 
  "PUSH1 0x00 ", 
  "SWAP1 ", 
  "SLOAD ", 
  "SWAP1 ", 
  "PUSH2 0x0100 ", 
  "EXP ", 
  "SWAP1 ", 
  "DIV ", 
  "PUSH20 0xffffffffffffffffffffffffffffffffffffffff ", 
  "AND ", 
  "DUP2 ", 
  "JUMP ", 
  "JUMPDEST ", 
  "PUSH1 0x00 ", 
  "DUP1 ", 
  "PUSH1 0x00 ", 
  "SWAP1 ", 
  "SLOAD ", 
  "SWAP1 ", 
  "PUSH2 0x0100 ", 
  "EXP ", 
  "SWAP1 ", 
  "DIV ", 
  "PUSH20 0xffffffffffffffffffffffffffffffffffffffff ", 
  "AND ", 
  "PUSH20 0xffffffffffffffffffffffffffffffffffffffff ", 
  "AND ", 
  "CALLER ", 
  "PUSH20 0xffffffffffffffffffffffffffffffffffffffff ", 
  "AND ", 
  "EQ ", 
  "ISZERO ", 
  "ISZERO ", 
  "PUSH2 0x141a ", 
  "JUMPI ", 
  "PUSH1 0x00 ", 
  "DUP1 ", 
  "REVERT ", 
  "JUMPDEST ", 
  "DUP3 ", 
  "PUSH20 0xffffffffffffffffffffffffffffffffffffffff ", 
  "AND ", 
  "PUSH4 0xa9059cbb ", 
  "PUSH1 0x00 ", 
  "DUP1 ", 
  "SWAP1 ", 
  "SLOAD ", 
  "SWAP1 ", 
  "PUSH2 0x0100 ", 
  "EXP ", 
  "SWAP1 ", 
  "DIV ", 
  "PUSH20 0xffffffffffffffffffffffffffffffffffffffff ", 
  "AND ", 
  "DUP5 ", 
  "PUSH1 0x40 ", 
  "MLOAD ", 
  "DUP4 ", 
  "PUSH4 0xffffffff ", 
  "AND ", 
  "PUSH29 0x0100000000000000000000000000000000000000000000000000000000 ", 
  "AND ", 
  "EQ ", 
  "ISZERO ", 
  "MUL ", 
  "DUP2 ", 
  "MSTORE ", 
  "PUSH1 0x04 ", 
  "ADD ", 
  "DUP1 ", 
  "DUP4 ", 
  "PUSH20 0xffffffffffffffffffffffffffffffffffffffff ", 
  "PUSH2 0x161f ", 
  "AND ", 
  "JUMPI ", 
  "AND ", 
  "PUSH20 0xffffffffffffffffffffffffffffffffffffffff ", 
  "PUSH1 0x00 ", 
  "DUP1 ", 
  "SWAP1 ", 
  "AND ", 
  "DUP2 ", 
  "MSTORE ", 
  "PUSH1 0x20 ", 
  "ADD ", 
  "DUP3 ", 
  "DUP2 ", 
  "MSTORE ", 
  "PUSH1 0x20 ", 
  "ADD ", 
  "SWAP3 ", 
  "POP ", 
  "POP ", 
  "POP ", 
  "PUSH1 0x20 ", 
  "PUSH1 0x40 ", 
  "MLOAD ", 
  "DUP1 ", 
  "DUP4 ", 
  "SUB ", 
  "DUP2 ", 
  "PUSH1 0x00 ", 
  "DUP8 ", 
  "DUP1 ", 
  "EXTCODESIZE ", 
  "ISZERO ", 
  "DUP1 ", 
  "ISZERO ", 
  "PUSH2 0x14de ", 
  "JUMPI ", 
  "PUSH1 0x00 ", 
  "DUP1 ", 
  "REVERT ", 
  "JUMPDEST ", 
  "POP ", 
  "GAS ", 
  "CALL ", 
  "ISZERO ", 
  "DUP1 ", 
  "ISZERO ", 
  "PUSH2 0x14f2 ", 
  "JUMPI ", 
  "RETURNDATASIZE ", 
  "PUSH1 0x00 ", 
  "DUP1 ", 
  "RETURNDATACOPY ", 
  "RETURNDATASIZE ", 
  "PUSH1 0x00 ", 
  "REVERT ", 
  "JUMPDEST ", 
  "POP ", 
  "POP ", 
  "POP ", 
  "POP ", 
  "PUSH1 0x40 ", 
  "MLOAD ", 
  "RETURNDATASIZE ", 
  "PUSH1 0x20 ", 
  "DUP2 ", 
  "LT ", 
  "ISZERO ", 
  "PUSH2 0x1508 ", 
  "JUMPI ", 
  "PUSH1 0x00 ", 
  "DUP1 ", 
  "REVERT ", 
  "JUMPDEST ", 
  "DUP2 ", 
  "ADD ", 
  "SWAP1 ", 
  "DUP1 ", 
  "DUP1 ", 
  "MLOAD ", 
  "SWAP1 ", 
  "PUSH1 0x20 ", 
  "ADD ", 
  "SWAP1 ", 
  "SWAP3 ", 
  "SWAP2 ", 
  "SWAP1 ", 
  "POP ", 
  "POP ", 
  "POP ", 
  "SWAP1 ", 
  "POP ", 
  "SWAP3 ", 
  "SWAP2 ", 
  "POP ", 
  "POP ", 
  "JUMP ", 
  "JUMPDEST ", 
  "PUSH1 0x00 ", 
  "PUSH1 0x07 ", 
  "PUSH1 0x00 ", 
  "DUP5 ", 
  "PUSH20 0xffffffffffffffffffffffffffffffffffffffff ", 
  "AND ", 
  "PUSH20 0xffffffffffffffffffffffffffffffffffffffff ", 
  "AND ", 
  "DUP2 ", 
  "MSTORE ", 
  "PUSH1 0x20 ", 
  "ADD ", 
  "SWAP1 ", 
  "DUP2 ", 
  "MSTORE ", 
  "PUSH1 0x20 ", 
  "ADD ", 
  "PUSH1 0x00 ", 
  "SHA3 ", 
  "PUSH1 0x00 ", 
  "DUP4 ", 
  "PUSH20 0xffffffffffffffffffffffffffffffffffffffff ", 
  "PUSH1 0x00 ", 
  "DUP1 ", 
  "REVERT ", 
  "AND ", 
  "PUSH20 0xffffffffffffffffffffffffffffffffffffffff ", 
  "MUL ", 
  "MUL ", 
  "NOT ", 
  "AND ", 
  "DUP2 ", 
  "MSTORE ", 
  "PUSH1 0x20 ", 
  "ADD ", 
  "SWAP1 ", 
  "DUP2 ", 
  "MSTORE ", 
  "PUSH1 0x20 ", 
  "ADD ", 
  "PUSH1 0x00 ", 
  "SHA3 ", 
  "SLOAD ", 
  "SWAP1 ", 
  "POP ", 
  "SWAP3 ", 
  "SWAP2 ", 
  "POP ", 
  "POP ", 
  "JUMP ", 
  "JUMPDEST ", 
  "PUSH1 0x00 ", 
  "DUP1 ", 
  "SWAP1 ", 
  "SLOAD ", 
  "SWAP1 ", 
  "PUSH2 0x0100 ", 
  "EXP ", 
  "SWAP1 ", 
  "DIV ", 
  "PUSH20 0xffffffffffffffffffffffffffffffffffffffff ", 
  "AND ", 
  "PUSH20 0xffffffffffffffffffffffffffffffffffffffff ", 
  "AND ", 
  "CALLER ", 
  "PUSH20 0xffffffffffffffffffffffffffffffffffffffff ", 
  "JUMPDEST ", 
  "CALLVALUE ", 
  "DUP1 ", 
  "ISZERO ", 
  "PUSH2 0x061f ", 
  "JUMPI ", 
  "PUSH1 0x00 ", 
  "OR ", 
  "DUP1 ", 
  "REVERT ", 
  "JUMPDEST ", 
  "POP ", 
  "PUSH2 0x0648 ", 
  "PUSH1 0x00 ", 
  "PUSH1 0x04 ", 
  "PUSH2 0x0100 ", 
  "DUP1 ", 
  "CALLDATASIZE ", 
  "SUB ", 
  "DUP2 ", 
  "ADD ", 
  "SWAP1 ", 
  "DUP1 ", 
  "DUP1 ", 
  "CALLDATALOAD ", 
  "SWAP1 ", 
  "PUSH1 0x20 ", 
  "ADD ", 
  "SWAP1 ", 
  "SWAP3 ", 
  "SWAP2 ", 
  "SWAP1 ", 
  "DUP1 ", 
  "CALLDATALOAD ", 
  "SWAP1 ", 
  "PUSH1 0x20 ", 
  "SSTORE ", 
  "ADD ", 
  "SWAP1 ", 
  "SWAP3 ", 
  "SWAP2 ", 
  "SWAP1 ", 
  "POP ", 
  "POP ", 
  "POP ", 
  "PUSH2 0x1366 ", 
  "DUP4 ", 
  "PUSH20 0xffffffffffffffffffffffffffffffffffffffff ", 
  "JUMP ", 
  "JUMPDEST ", 
  "PUSH1 0x40 ", 
  "MLOAD ", 
  "DUP1 ", 
  "DUP3 ", 
  "DUP2 ", 
  "MSTORE ", 
  "PUSH1 0x20 ", 
  "ADD ", 
  "SWAP2 ", 
  "POP ", 
  "POP ", 
  "PUSH1 0x40 ", 
  "MLOAD ", 
  "DUP1 ", 
  "SWAP2 ", 
  "SUB ", 
  "SWAP1 ", 
  "RETURN ", 
  "JUMPDEST ", 
  "CALLVALUE ", 
  "DUP1 ", 
  "ISZERO ", 
  "PUSH2 0x066a ", 
  "STOP ", 
  "JUMPI ", 
  "PUSH1 0x00 ", 
  "DUP1 ", 
  "REVERT ", 
  "JUMPDEST ", 
  "POP ", 
  "PUSH2 0x0673 ", 
  "PUSH2 0x1397 ", 
  "JUMP ", 
  "JUMPDEST ", 
  "PUSH1 0x40 ", 
  "MLOAD ", 
  "DUP1 ", 
  "DUP3 ", 
  "PUSH20 0xffffffffffffffffffffffffffffffffffffffff ", 
  "AND ", 
  "PUSH20 0xffffffffffffffffffffffffffffffffffffffff ", 
  "AND ", 
  "DUP2 ", 
  "MSTORE ", 
  "PUSH1 0x20 ", 
  "ADD ", 
  "SWAP2 ", 
  "POP ", 
  "POP ", 
  "PUSH1 0x40 ", 
  "MLOAD ", 
  "DUP1 ", 
  "SWAP2 ", 
  "SUB ", 
  "SWAP1 ", 
  "RETURN ", 
  "JUMPDEST ", 
  "CALLVALUE ", 
  "DUP1 ", 
  "ISZERO ", 
  "PUSH2 0x06c1 ", 
  "JUMPI ", 
  "PUSH1 0x00 ", 
  "DUP1 ", 
  "REVERT ", 
  "JUMPDEST ", 
  "POP ", 
  "PUSH2 0x0700 ", 
  "PUSH1 0x04 ", 
  "DUP1 ", 
  "CALLDATASIZE ", 
  "SUB ", 
  "DUP2 ", 
  "ADD ", 
  "SWAP1 ", 
  "DUP1 ", 
  "DUP1 ", 
  "CALLDATALOAD ", 
  "PUSH20 0xffffffffffffffffffffffffffffffffffffffff ", 
  "AND ", 
  "SWAP1 ", 
  "PUSH1 0x20 ", 
  "ADD ", 
  "SWAP1 ", 
  "SWAP3 ", 
  "SWAP2 ", 
  "SWAP1 ", 
  "DUP1 ", 
  "CALLDATALOAD ", 
  "SWAP1 ", 
  "PUSH1 0x20 ", 
  "ADD ", 
  "SWAP1 ", 
  "SWAP3 ", 
  "SWAP2 ", 
  "SWAP1 ", 
  "POP ", 
  "POP ", 
  "POP ", 
  "PUSH2 0x13bd ", 
  "JUMP ", 
  "JUMPDEST ", 
  "PUSH1 0x40 ", 
  "MLOAD ", 
  "DUP1 ", 
  "DUP3 ", 
  "ISZERO ", 
  "ISZERO ", 
  "ISZERO ", 
  "ISZERO ", 
  "DUP2 ", 
  "MSTORE ", 
  "PUSH1 0x20 ", 
  "ADD ", 
  "SWAP2 ", 
  "POP ", 
  "POP ", 
  "PUSH1 0x40 ", 
  "MLOAD ", 
  "DUP1 ", 
  "SWAP2 ", 
  "SUB ", 
  "SWAP1 ", 
  "RETURN ", 
  "JUMPDEST ", 
  "CALLVALUE ", 
  "DUP1 ", 
  "ISZERO ", 
  "PUSH2 0x0726 ", 
  "JUMPI ", 
  "PUSH1 0x00 ", 
  "DUP1 ", 
  "REVERT ", 
  "JUMPDEST ", 
  "POP ", 
  "PUSH2 0x077b ", 
  "PUSH1 0x04 ", 
  "DUP1 ", 
  "CALLDATASIZE ", 
  "SUB ", 
  "DUP2 ", 
  "ADD ", 
  "SWAP1 ", 
  "DUP1 ", 
  "DUP1 ", 
  "CALLDATALOAD ", 
  "PUSH20 0xffffffffffffffffffffffffffffffffffffffff ", 
  "ISZERO ", 
  "AND ", 
  "SWAP1 ", 
  "PUSH1 0x20 ", 
  "ADD ", 
  "SWAP1 ", 
  "SWAP3 ", 
  "SWAP2 ", 
  "SWAP1 ", 
  "DUP1 ", 
  "CALLDATALOAD ", 
  "PUSH20 0xffffffffffffffffffffffffffffffffffffffff ", 
  "AND ", 
  "AND ", 
  "SWAP1 ", 
  "PUSH1 0x20 ", 
  "ADD ", 
  "SWAP1 ", 
  "SWAP3 ", 
  "SWAP2 ", 
  "SWAP1 ", 
  "POP ", 
  "POP ", 
  "POP ", 
  "PUSH2 0x1521 ", 
  "JUMP ", 
  "JUMPDEST ", 
  "PUSH1 0x40 ", 
  "MLOAD ", 
  "DUP1 ", 
  "DUP3 ", 
  "DUP2 ", 
  "MSTORE ", 
  "PUSH1 0x20 ", 
  "ADD ", 
  "SWAP2 ", 
  "POP ", 
  "POP ", 
  "PUSH1 0x40 ", 
  "MLOAD ", 
  "DUP1 ", 
  "SWAP2 ", 
  "SUB ", 
  "SWAP1 ", 
  "RETURN ", 
  "JUMPDEST ", 
  "CALLVALUE ", 
  "DUP1 ", 
  "ISZERO ", 
  "PUSH2 0x079d ", 
  "JUMPI ", 
  "PUSH1 0x00 ", 
  "DUP1 ", 
  "REVERT ", 
  "JUMPDEST ", 
  "POP ", 
  "PUSH2 0x07c6 ", 
  "PUSH1 0x04 ", 
  "DUP1 ", 
  "CALLDATASIZE ", 
  "SUB ", 
  "DUP2 ", 
  "ADD ", 
  "SWAP1 ", 
  "DUP1 ", 
  "DUP1 ", 
  "CALLDATALOAD ", 
  "SWAP1 ", 
  "PUSH1 0x20 ", 
  "ADD ", 
  "SWAP1 ", 
  "SWAP3 ", 
  "SWAP2 ", 
  "SWAP1 ", 
  "DUP1 ", 
  "CALLDATALOAD ", 
  "SWAP1 ", 
  "PUSH1 0x20 ", 
  "ADD ", 
  "SWAP1 ", 
  "SWAP3 ", 
  "SWAP2 ", 
  "SWAP1 ", 
  "POP ", 
  "POP ", 
  "POP ", 
  "PUSH2 0x15a8 ", 
  "JUMP ", 
  "JUMPDEST ", 
  "PUSH1 0x40 ", 
  "MLOAD ", 
  "DUP1 ", 
  "DUP3 ", 
  "DUP2 ", 
  "MSTORE ", 
  "PUSH1 0x20 ", 
  "ADD ", 
  "SWAP2 ", 
  "POP ", 
  "POP ", 
  "PUSH1 0x40 ", 
  "MLOAD ", 
  "DUP1 ", 
  "SWAP2 ", 
  "SUB ", 
  "SWAP1 ", 
  "RETURN ", 
  "JUMPDEST ", 
  "CALLVALUE ", 
  "DUP1 ", 
  "ISZERO ", 
  "PUSH2 0x07e8 ", 
  "JUMPI ", 
  "PUSH1 0x00 ", 
  "DUP1 ", 
  "REVERT ", 
  "JUMPDEST ", 
  "POP ", 
  "PUSH2 0x081d ", 
  "PUSH1 0x04 ", 
  "DUP1 ", 
  "CALLDATASIZE ", 
  "SUB ", 
  "DUP2 ", 
  "ADD ", 
  "SWAP1 ", 
  "DUP1 ", 
  "DUP1 ", 
  "CALLDATALOAD ", 
  "PUSH20 0xffffffffffffffffffffffffffffffffffffffff ", 
  "POP "
 ], 
 "overflow": false, 
 "money_concurrency": false, 
 "truncation": false
},"Owned-7":{
 "execution_paths": "12", 
 "callstack": false, 
 "reentrancy": false, 
 "modulo": false, 
 "division": false, 
 "execution_time": "0.56271314621", 
 "signedness": false, 
 "evm_code_coverage": "99.7", 
 "underflow": false, 
 "time_dependency": false, 
 "assertion_failure": false, 
 "timeout": false, 
 "dead_code": [
  "STOP "
 ], 
 "overflow": false, 
 "money_concurrency": false, 
 "truncation": false
},"SafeMath-7":{
 "execution_paths": "16", 
 "callstack": false, 
 "reentrancy": false, 
 "modulo": false, 
 "division": false, 
 "execution_time": "9.39689087868", 
 "signedness": false, 
 "evm_code_coverage": "99.8", 
 "underflow": false, 
 "time_dependency": false, 
 "assertion_failure": false, 
 "timeout": false, 
 "dead_code": [
  "STOP "
 ], 
 "overflow": false, 
 "money_concurrency": false, 
 "truncation": false
},"Hubscop-8":{
 "execution_paths": "65", 
 "callstack": false, 
 "reentrancy": false, 
 "modulo": false, 
 "division": false, 
 "execution_time": "50.0831770897", 
 "signedness": false, 
 "evm_code_coverage": "76.8", 
 "underflow": "\n./0x001fc4a7f2f586596308091c7b296d4535a25a90_ext.sol:Hubscop:103:16\n_totalSupply  - balances[address(0)]\n^", 
 "time_dependency": false, 
 "assertion_failure": false, 
 "timeout": true, 
 "dead_code": [
  "AND ", 
  "SWAP1 ", 
  "PUSH1 0x20 ", 
  "ADD ", 
  "SWAP1 ", 
  "SWAP3 ", 
  "SWAP2 ", 
  "SWAP1 ", 
  "POP ", 
  "POP ", 
  "POP ", 
  "PUSH2 0x15c4 ", 
  "JUMP ", 
  "JUMPDEST ", 
  "STOP ", 
  "JUMP ", 
  "REVERT ", 
  "JUMPDEST ", 
  "DUP1 ", 
  "POP ", 
  "PUSH1 0x01 ", 
  "DUP1 ", 
  "PUSH4 0xd05c78da ", 
  "EQ ", 
  "PUSH2 0x0613 ", 
  "JUMPI ", 
  "DUP1 ", 
  "PUSH4 0xd4ee1d90 ", 
  "EQ ", 
  "PUSH2 0x065e ", 
  "JUMPI ", 
  "DUP1 ", 
  "PUSH4 0xdc39d06d ", 
  "EQ ", 
  "PUSH2 0x06b5 ", 
  "JUMPI ", 
  "DUP1 ", 
  "PUSH4 0xdd62ed3e ", 
  "EQ ", 
  "PUSH2 0x071a ", 
  "JUMPI ", 
  "DUP1 ", 
  "PUSH4 0xe6cb9013 ", 
  "EQ ", 
  "PUSH2 0x0791 ", 
  "JUMPI ", 
  "DUP1 ", 
  "PUSH4 0xf2fde38b ", 
  "EQ ", 
  "PUSH2 0x07dc ", 
  "JUMPI ", 
  "EXP ", 
  "SWAP1 ", 
  "DUP2 ", 
  "SLOAD ", 
  "DUP2 ", 
  "PUSH20 0xffffffffffffffffffffffffffffffffffffffff ", 
  "JUMPDEST ", 
  "PUSH1 0x00 ", 
  "DUP2 ", 
  "DUP4 ", 
  "MUL ", 
  "SWAP1 ", 
  "POP ", 
  "PUSH1 0x00 ", 
  "DUP4 ", 
  "EQ ", 
  "DUP1 ", 
  "PUSH2 0x1386 ", 
  "JUMPI ", 
  "POP ", 
  "DUP2 ", 
  "DUP4 ", 
  "DUP3 ", 
  "DUP2 ", 
  "ISZERO ", 
  "ISZERO ", 
  "PUSH2 0x1383 ", 
  "JUMPI ", 
  "ASSERTFAIL ", 
  "JUMPDEST ", 
  "DIV ", 
  "EQ ", 
  "JUMPDEST ", 
  "ISZERO ", 
  "ISZERO ", 
  "PUSH2 0x1391 ", 
  "JUMPI ", 
  "PUSH1 0x00 ", 
  "DUP1 ", 
  "REVERT ", 
  "JUMPDEST ", 
  "SWAP3 ", 
  "SWAP2 ", 
  "POP ", 
  "POP ", 
  "JUMP ", 
  "JUMPDEST ", 
  "PUSH1 0x01 ", 
  "PUSH1 0x00 ", 
  "SWAP1 ", 
  "SLOAD ", 
  "SWAP1 ", 
  "PUSH2 0x0100 ", 
  "EXP ", 
  "SWAP1 ", 
  "DIV ", 
  "PUSH20 0xffffffffffffffffffffffffffffffffffffffff ", 
  "AND ", 
  "DUP2 ", 
  "JUMP ", 
  "JUMPDEST ", 
  "PUSH1 0x00 ", 
  "DUP1 ", 
  "PUSH1 0x00 ", 
  "SWAP1 ", 
  "SLOAD ", 
  "SWAP1 ", 
  "PUSH2 0x0100 ", 
  "EXP ", 
  "SWAP1 ", 
  "DIV ", 
  "PUSH20 0xffffffffffffffffffffffffffffffffffffffff ", 
  "AND ", 
  "PUSH20 0xffffffffffffffffffffffffffffffffffffffff ", 
  "AND ", 
  "CALLER ", 
  "PUSH20 0xffffffffffffffffffffffffffffffffffffffff ", 
  "AND ", 
  "EQ ", 
  "ISZERO ", 
  "ISZERO ", 
  "PUSH2 0x141a ", 
  "JUMPI ", 
  "PUSH1 0x00 ", 
  "DUP1 ", 
  "REVERT ", 
  "JUMPDEST ", 
  "DUP3 ", 
  "PUSH20 0xffffffffffffffffffffffffffffffffffffffff ", 
  "AND ", 
  "PUSH4 0xa9059cbb ", 
  "PUSH1 0x00 ", 
  "DUP1 ", 
  "SWAP1 ", 
  "SLOAD ", 
  "SWAP1 ", 
  "PUSH2 0x0100 ", 
  "EXP ", 
  "SWAP1 ", 
  "DIV ", 
  "PUSH20 0xffffffffffffffffffffffffffffffffffffffff ", 
  "AND ", 
  "DUP5 ", 
  "PUSH1 0x40 ", 
  "MLOAD ", 
  "DUP4 ", 
  "PUSH4 0xffffffff ", 
  "AND ", 
  "PUSH29 0x0100000000000000000000000000000000000000000000000000000000 ", 
  "AND ", 
  "EQ ", 
  "ISZERO ", 
  "MUL ", 
  "DUP2 ", 
  "MSTORE ", 
  "PUSH1 0x04 ", 
  "ADD ", 
  "DUP1 ", 
  "DUP4 ", 
  "PUSH20 0xffffffffffffffffffffffffffffffffffffffff ", 
  "PUSH2 0x161f ", 
  "AND ", 
  "JUMPI ", 
  "AND ", 
  "PUSH20 0xffffffffffffffffffffffffffffffffffffffff ", 
  "PUSH1 0x00 ", 
  "DUP1 ", 
  "SWAP1 ", 
  "AND ", 
  "DUP2 ", 
  "MSTORE ", 
  "PUSH1 0x20 ", 
  "ADD ", 
  "DUP3 ", 
  "DUP2 ", 
  "MSTORE ", 
  "PUSH1 0x20 ", 
  "ADD ", 
  "SWAP3 ", 
  "POP ", 
  "POP ", 
  "POP ", 
  "PUSH1 0x20 ", 
  "PUSH1 0x40 ", 
  "MLOAD ", 
  "DUP1 ", 
  "DUP4 ", 
  "SUB ", 
  "DUP2 ", 
  "PUSH1 0x00 ", 
  "DUP8 ", 
  "DUP1 ", 
  "EXTCODESIZE ", 
  "ISZERO ", 
  "DUP1 ", 
  "ISZERO ", 
  "PUSH2 0x14de ", 
  "JUMPI ", 
  "PUSH1 0x00 ", 
  "DUP1 ", 
  "REVERT ", 
  "JUMPDEST ", 
  "POP ", 
  "GAS ", 
  "CALL ", 
  "ISZERO ", 
  "DUP1 ", 
  "ISZERO ", 
  "PUSH2 0x14f2 ", 
  "JUMPI ", 
  "RETURNDATASIZE ", 
  "PUSH1 0x00 ", 
  "DUP1 ", 
  "RETURNDATACOPY ", 
  "RETURNDATASIZE ", 
  "PUSH1 0x00 ", 
  "REVERT ", 
  "JUMPDEST ", 
  "POP ", 
  "POP ", 
  "POP ", 
  "POP ", 
  "PUSH1 0x40 ", 
  "MLOAD ", 
  "RETURNDATASIZE ", 
  "PUSH1 0x20 ", 
  "DUP2 ", 
  "LT ", 
  "ISZERO ", 
  "PUSH2 0x1508 ", 
  "JUMPI ", 
  "PUSH1 0x00 ", 
  "DUP1 ", 
  "REVERT ", 
  "JUMPDEST ", 
  "DUP2 ", 
  "ADD ", 
  "SWAP1 ", 
  "DUP1 ", 
  "DUP1 ", 
  "MLOAD ", 
  "SWAP1 ", 
  "PUSH1 0x20 ", 
  "ADD ", 
  "SWAP1 ", 
  "SWAP3 ", 
  "SWAP2 ", 
  "SWAP1 ", 
  "POP ", 
  "POP ", 
  "POP ", 
  "SWAP1 ", 
  "POP ", 
  "SWAP3 ", 
  "SWAP2 ", 
  "POP ", 
  "POP ", 
  "JUMP ", 
  "JUMPDEST ", 
  "PUSH1 0x00 ", 
  "PUSH1 0x07 ", 
  "PUSH1 0x00 ", 
  "DUP5 ", 
  "PUSH20 0xffffffffffffffffffffffffffffffffffffffff ", 
  "AND ", 
  "PUSH20 0xffffffffffffffffffffffffffffffffffffffff ", 
  "AND ", 
  "DUP2 ", 
  "MSTORE ", 
  "PUSH1 0x20 ", 
  "ADD ", 
  "SWAP1 ", 
  "DUP2 ", 
  "MSTORE ", 
  "PUSH1 0x20 ", 
  "ADD ", 
  "PUSH1 0x00 ", 
  "SHA3 ", 
  "PUSH1 0x00 ", 
  "DUP4 ", 
  "PUSH20 0xffffffffffffffffffffffffffffffffffffffff ", 
  "PUSH1 0x00 ", 
  "DUP1 ", 
  "REVERT ", 
  "AND ", 
  "PUSH20 0xffffffffffffffffffffffffffffffffffffffff ", 
  "MUL ", 
  "MUL ", 
  "NOT ", 
  "AND ", 
  "DUP2 ", 
  "MSTORE ", 
  "PUSH1 0x20 ", 
  "ADD ", 
  "SWAP1 ", 
  "DUP2 ", 
  "MSTORE ", 
  "PUSH1 0x20 ", 
  "ADD ", 
  "PUSH1 0x00 ", 
  "SHA3 ", 
  "SLOAD ", 
  "SWAP1 ", 
  "POP ", 
  "SWAP3 ", 
  "SWAP2 ", 
  "POP ", 
  "POP ", 
  "JUMP ", 
  "JUMPDEST ", 
  "PUSH1 0x00 ", 
  "DUP1 ", 
  "SWAP1 ", 
  "SLOAD ", 
  "SWAP1 ", 
  "PUSH2 0x0100 ", 
  "EXP ", 
  "SWAP1 ", 
  "DIV ", 
  "PUSH20 0xffffffffffffffffffffffffffffffffffffffff ", 
  "AND ", 
  "PUSH20 0xffffffffffffffffffffffffffffffffffffffff ", 
  "AND ", 
  "CALLER ", 
  "PUSH20 0xffffffffffffffffffffffffffffffffffffffff ", 
  "JUMPDEST ", 
  "CALLVALUE ", 
  "DUP1 ", 
  "ISZERO ", 
  "PUSH2 0x061f ", 
  "JUMPI ", 
  "PUSH1 0x00 ", 
  "OR ", 
  "DUP1 ", 
  "REVERT ", 
  "JUMPDEST ", 
  "POP ", 
  "PUSH2 0x0648 ", 
  "PUSH1 0x00 ", 
  "PUSH1 0x04 ", 
  "PUSH2 0x0100 ", 
  "DUP1 ", 
  "CALLDATASIZE ", 
  "SUB ", 
  "DUP2 ", 
  "ADD ", 
  "SWAP1 ", 
  "DUP1 ", 
  "DUP1 ", 
  "CALLDATALOAD ", 
  "SWAP1 ", 
  "PUSH1 0x20 ", 
  "ADD ", 
  "SWAP1 ", 
  "SWAP3 ", 
  "SWAP2 ", 
  "SWAP1 ", 
  "DUP1 ", 
  "CALLDATALOAD ", 
  "SWAP1 ", 
  "PUSH1 0x20 ", 
  "SSTORE ", 
  "ADD ", 
  "SWAP1 ", 
  "SWAP3 ", 
  "SWAP2 ", 
  "SWAP1 ", 
  "POP ", 
  "POP ", 
  "POP ", 
  "PUSH2 0x1366 ", 
  "DUP4 ", 
  "PUSH20 0xffffffffffffffffffffffffffffffffffffffff ", 
  "JUMP ", 
  "JUMPDEST ", 
  "PUSH1 0x40 ", 
  "MLOAD ", 
  "DUP1 ", 
  "DUP3 ", 
  "DUP2 ", 
  "MSTORE ", 
  "PUSH1 0x20 ", 
  "ADD ", 
  "SWAP2 ", 
  "POP ", 
  "POP ", 
  "PUSH1 0x40 ", 
  "MLOAD ", 
  "DUP1 ", 
  "SWAP2 ", 
  "SUB ", 
  "SWAP1 ", 
  "RETURN ", 
  "JUMPDEST ", 
  "CALLVALUE ", 
  "DUP1 ", 
  "ISZERO ", 
  "PUSH2 0x066a ", 
  "STOP ", 
  "JUMPI ", 
  "PUSH1 0x00 ", 
  "DUP1 ", 
  "REVERT ", 
  "JUMPDEST ", 
  "POP ", 
  "PUSH2 0x0673 ", 
  "PUSH2 0x1397 ", 
  "JUMP ", 
  "JUMPDEST ", 
  "PUSH1 0x40 ", 
  "MLOAD ", 
  "DUP1 ", 
  "DUP3 ", 
  "PUSH20 0xffffffffffffffffffffffffffffffffffffffff ", 
  "AND ", 
  "PUSH20 0xffffffffffffffffffffffffffffffffffffffff ", 
  "AND ", 
  "DUP2 ", 
  "MSTORE ", 
  "PUSH1 0x20 ", 
  "ADD ", 
  "SWAP2 ", 
  "POP ", 
  "POP ", 
  "PUSH1 0x40 ", 
  "MLOAD ", 
  "DUP1 ", 
  "SWAP2 ", 
  "SUB ", 
  "SWAP1 ", 
  "RETURN ", 
  "JUMPDEST ", 
  "CALLVALUE ", 
  "DUP1 ", 
  "ISZERO ", 
  "PUSH2 0x06c1 ", 
  "JUMPI ", 
  "PUSH1 0x00 ", 
  "DUP1 ", 
  "REVERT ", 
  "JUMPDEST ", 
  "POP ", 
  "PUSH2 0x0700 ", 
  "PUSH1 0x04 ", 
  "DUP1 ", 
  "CALLDATASIZE ", 
  "SUB ", 
  "DUP2 ", 
  "ADD ", 
  "SWAP1 ", 
  "DUP1 ", 
  "DUP1 ", 
  "CALLDATALOAD ", 
  "PUSH20 0xffffffffffffffffffffffffffffffffffffffff ", 
  "AND ", 
  "SWAP1 ", 
  "PUSH1 0x20 ", 
  "ADD ", 
  "SWAP1 ", 
  "SWAP3 ", 
  "SWAP2 ", 
  "SWAP1 ", 
  "DUP1 ", 
  "CALLDATALOAD ", 
  "SWAP1 ", 
  "PUSH1 0x20 ", 
  "ADD ", 
  "SWAP1 ", 
  "SWAP3 ", 
  "SWAP2 ", 
  "SWAP1 ", 
  "POP ", 
  "POP ", 
  "POP ", 
  "PUSH2 0x13bd ", 
  "JUMP ", 
  "JUMPDEST ", 
  "PUSH1 0x40 ", 
  "MLOAD ", 
  "DUP1 ", 
  "DUP3 ", 
  "ISZERO ", 
  "ISZERO ", 
  "ISZERO ", 
  "ISZERO ", 
  "DUP2 ", 
  "MSTORE ", 
  "PUSH1 0x20 ", 
  "ADD ", 
  "SWAP2 ", 
  "POP ", 
  "POP ", 
  "PUSH1 0x40 ", 
  "MLOAD ", 
  "DUP1 ", 
  "SWAP2 ", 
  "SUB ", 
  "SWAP1 ", 
  "RETURN ", 
  "JUMPDEST ", 
  "CALLVALUE ", 
  "DUP1 ", 
  "ISZERO ", 
  "PUSH2 0x0726 ", 
  "JUMPI ", 
  "PUSH1 0x00 ", 
  "DUP1 ", 
  "REVERT ", 
  "JUMPDEST ", 
  "POP ", 
  "PUSH2 0x077b ", 
  "PUSH1 0x04 ", 
  "DUP1 ", 
  "CALLDATASIZE ", 
  "SUB ", 
  "DUP2 ", 
  "ADD ", 
  "SWAP1 ", 
  "DUP1 ", 
  "DUP1 ", 
  "CALLDATALOAD ", 
  "PUSH20 0xffffffffffffffffffffffffffffffffffffffff ", 
  "ISZERO ", 
  "AND ", 
  "SWAP1 ", 
  "PUSH1 0x20 ", 
  "ADD ", 
  "SWAP1 ", 
  "SWAP3 ", 
  "SWAP2 ", 
  "SWAP1 ", 
  "DUP1 ", 
  "CALLDATALOAD ", 
  "PUSH20 0xffffffffffffffffffffffffffffffffffffffff ", 
  "AND ", 
  "AND ", 
  "SWAP1 ", 
  "PUSH1 0x20 ", 
  "ADD ", 
  "SWAP1 ", 
  "SWAP3 ", 
  "SWAP2 ", 
  "SWAP1 ", 
  "POP ", 
  "POP ", 
  "POP ", 
  "PUSH2 0x1521 ", 
  "JUMP ", 
  "JUMPDEST ", 
  "PUSH1 0x40 ", 
  "MLOAD ", 
  "DUP1 ", 
  "DUP3 ", 
  "DUP2 ", 
  "MSTORE ", 
  "PUSH1 0x20 ", 
  "ADD ", 
  "SWAP2 ", 
  "POP ", 
  "POP ", 
  "PUSH1 0x40 ", 
  "MLOAD ", 
  "DUP1 ", 
  "SWAP2 ", 
  "SUB ", 
  "SWAP1 ", 
  "RETURN ", 
  "JUMPDEST ", 
  "CALLVALUE ", 
  "DUP1 ", 
  "ISZERO ", 
  "PUSH2 0x079d ", 
  "JUMPI ", 
  "PUSH1 0x00 ", 
  "DUP1 ", 
  "REVERT ", 
  "JUMPDEST ", 
  "POP ", 
  "PUSH2 0x07c6 ", 
  "PUSH1 0x04 ", 
  "DUP1 ", 
  "CALLDATASIZE ", 
  "SUB ", 
  "DUP2 ", 
  "ADD ", 
  "SWAP1 ", 
  "DUP1 ", 
  "DUP1 ", 
  "CALLDATALOAD ", 
  "SWAP1 ", 
  "PUSH1 0x20 ", 
  "ADD ", 
  "SWAP1 ", 
  "SWAP3 ", 
  "SWAP2 ", 
  "SWAP1 ", 
  "DUP1 ", 
  "CALLDATALOAD ", 
  "SWAP1 ", 
  "PUSH1 0x20 ", 
  "ADD ", 
  "SWAP1 ", 
  "SWAP3 ", 
  "SWAP2 ", 
  "SWAP1 ", 
  "POP ", 
  "POP ", 
  "POP ", 
  "PUSH2 0x15a8 ", 
  "JUMP ", 
  "JUMPDEST ", 
  "PUSH1 0x40 ", 
  "MLOAD ", 
  "DUP1 ", 
  "DUP3 ", 
  "DUP2 ", 
  "MSTORE ", 
  "PUSH1 0x20 ", 
  "ADD ", 
  "SWAP2 ", 
  "POP ", 
  "POP ", 
  "PUSH1 0x40 ", 
  "MLOAD ", 
  "DUP1 ", 
  "SWAP2 ", 
  "SUB ", 
  "SWAP1 ", 
  "RETURN ", 
  "JUMPDEST ", 
  "CALLVALUE ", 
  "DUP1 ", 
  "ISZERO ", 
  "PUSH2 0x07e8 ", 
  "JUMPI ", 
  "PUSH1 0x00 ", 
  "DUP1 ", 
  "REVERT ", 
  "JUMPDEST ", 
  "POP ", 
  "PUSH2 0x081d ", 
  "PUSH1 0x04 ", 
  "DUP1 ", 
  "CALLDATASIZE ", 
  "SUB ", 
  "DUP2 ", 
  "ADD ", 
  "SWAP1 ", 
  "DUP1 ", 
  "DUP1 ", 
  "CALLDATALOAD ", 
  "PUSH20 0xffffffffffffffffffffffffffffffffffffffff ", 
  "POP "
 ], 
 "overflow": false, 
 "money_concurrency": false, 
 "truncation": false
},"Owned-8":{
 "execution_paths": "12", 
 "callstack": false, 
 "reentrancy": false, 
 "modulo": false, 
 "division": false, 
 "execution_time": "0.817579030991", 
 "signedness": false, 
 "evm_code_coverage": "99.7", 
 "underflow": false, 
 "time_dependency": false, 
 "assertion_failure": false, 
 "timeout": false, 
 "dead_code": [
  "STOP "
 ], 
 "overflow": false, 
 "money_concurrency": false, 
 "truncation": false
},"SafeMath-8":{
 "execution_paths": "16", 
 "callstack": false, 
 "reentrancy": false, 
 "modulo": false, 
 "division": false, 
 "execution_time": "11.0015158653", 
 "signedness": false, 
 "evm_code_coverage": "99.8", 
 "underflow": false, 
 "time_dependency": false, 
 "assertion_failure": false, 
 "timeout": false, 
 "dead_code": [
  "STOP "
 ], 
 "overflow": false, 
 "money_concurrency": false, 
 "truncation": false
}}