{"CampaignContract-1":{
 "execution_paths": "106", 
 "callstack": false, 
 "reentrancy": false, 
 "modulo": false, 
 "division": false, 
 "execution_time": "10.1432058811", 
 "signedness": false, 
 "evm_code_coverage": "98.7", 
 "underflow": false, 
 "time_dependency": false, 
 "assertion_failure": false, 
 "timeout": false, 
 "dead_code": [
  "DUP2 ", 
  "SWAP1 ", 
  "SSTORE ", 
  "POP ", 
  "DUP4 ", 
  "PUSH1 0x03 ", 
  "SLOAD ", 
  "PUSH1 0x04 ", 
  "SLOAD ", 
  "PUSH32 0xcc8d22e807ea92fa44cbc984df35dfbb8351ddf6302b105e5e3cef56dbe45712 ", 
  "JUMPDEST ", 
  "STOP ", 
  "STOP ", 
  "PUSH1 0x40 ", 
  "MLOAD ", 
  "PUSH1 0x40 ", 
  "MLOAD ", 
  "DUP1 ", 
  "SWAP2 ", 
  "SUB ", 
  "SWAP1 ", 
  "LOG4 ", 
  "POP ", 
  "POP ", 
  "POP ", 
  "POP ", 
  "JUMP ", 
  "JUMPDEST ", 
  "JUMPDEST ", 
  "PUSH1 0x03 ", 
  "DUP2 ", 
  "SWAP1 ", 
  "SSTORE ", 
  "POP ", 
  "PUSH2 0x0a7d ", 
  "DUP4 ", 
  "DUP4 ", 
  "PUSH2 0x2010 ", 
  "SWAP1 ", 
  "SWAP2 ", 
  "SWAP1 ", 
  "PUSH4 0xffffffff ", 
  "STOP ", 
  "AND ", 
  "JUMP ", 
  "JUMPDEST ", 
  "PUSH1 0x04 "
 ], 
 "overflow": false, 
 "money_concurrency": "\nFlow 1:\n./0x009ef15c147ff4c0eb373e1abd2f4d184e5cb916_ext.sol:CampaignContract:182:3\nmsg.sender.transfer(amount)\n^\nFlow 2:", 
 "truncation": false
},"SafeMath-1":{
 "execution_paths": "1", 
 "callstack": false, 
 "reentrancy": false, 
 "modulo": false, 
 "division": false, 
 "execution_time": "0.0116229057312", 
 "signedness": false, 
 "evm_code_coverage": "100.0", 
 "underflow": false, 
 "time_dependency": false, 
 "assertion_failure": false, 
 "timeout": false, 
 "dead_code": [], 
 "overflow": false, 
 "money_concurrency": false, 
 "truncation": false
},"CampaignContract-2":{
 "execution_paths": "108", 
 "callstack": false, 
 "reentrancy": false, 
 "modulo": false, 
 "division": false, 
 "execution_time": "9.65217685699", 
 "signedness": false, 
 "evm_code_coverage": "98.8", 
 "underflow": false, 
 "time_dependency": false, 
 "assertion_failure": false, 
 "timeout": false, 
 "dead_code": [
  "JUMPDEST ", 
  "PUSH1 0x03 ", 
  "DUP2 ", 
  "SWAP1 ", 
  "SSTORE ", 
  "POP ", 
  "PUSH2 0x0b38 ", 
  "JUMPDEST ", 
  "DUP4 ", 
  "DUP4 ", 
  "PUSH2 0x2123 ", 
  "SWAP1 ", 
  "SWAP2 ", 
  "SWAP1 ", 
  "PUSH4 0xffffffff ", 
  "STOP ", 
  "STOP ", 
  "AND ", 
  "JUMP ", 
  "JUMPDEST ", 
  "PUSH1 0x04 ", 
  "DUP2 ", 
  "SWAP1 ", 
  "SSTORE ", 
  "POP ", 
  "DUP4 ", 
  "PUSH1 0x03 ", 
  "SLOAD ", 
  "PUSH1 0x04 ", 
  "SLOAD ", 
  "PUSH32 0xcc8d22e807ea92fa44cbc984df35dfbb8351ddf6302b105e5e3cef56dbe45712 ", 
  "PUSH1 0x40 ", 
  "MLOAD ", 
  "PUSH1 0x40 ", 
  "MLOAD ", 
  "DUP1 ", 
  "SWAP2 ", 
  "SUB ", 
  "SWAP1 ", 
  "LOG4 ", 
  "POP ", 
  "POP ", 
  "POP ", 
  "POP ", 
  "JUMP ", 
  "JUMPDEST ", 
  "STOP "
 ], 
 "overflow": false, 
 "money_concurrency": "\nFlow 1:\n./0x009ef15c147ff4c0eb373e1abd2f4d184e5cb916_ext.sol:CampaignContract:182:3\nmsg.sender.transfer(amount)\n^\nFlow 2:", 
 "truncation": false
},"SafeMath-2":{
 "execution_paths": "1", 
 "callstack": false, 
 "reentrancy": false, 
 "modulo": false, 
 "division": false, 
 "execution_time": "0.0087559223175", 
 "signedness": false, 
 "evm_code_coverage": "100.0", 
 "underflow": false, 
 "time_dependency": false, 
 "assertion_failure": false, 
 "timeout": false, 
 "dead_code": [], 
 "overflow": false, 
 "money_concurrency": false, 
 "truncation": false
},"CampaignContract-3":{
 "execution_paths": "108", 
 "callstack": false, 
 "reentrancy": false, 
 "modulo": false, 
 "division": false, 
 "execution_time": "8.38339304924", 
 "signedness": false, 
 "evm_code_coverage": "98.8", 
 "underflow": false, 
 "time_dependency": false, 
 "assertion_failure": false, 
 "timeout": false, 
 "dead_code": [
  "JUMPDEST ", 
  "PUSH1 0x03 ", 
  "DUP2 ", 
  "SWAP1 ", 
  "SSTORE ", 
  "POP ", 
  "PUSH2 0x0b38 ", 
  "JUMPDEST ", 
  "DUP4 ", 
  "DUP4 ", 
  "PUSH2 0x2123 ", 
  "SWAP1 ", 
  "SWAP2 ", 
  "SWAP1 ", 
  "PUSH4 0xffffffff ", 
  "STOP ", 
  "STOP ", 
  "AND ", 
  "JUMP ", 
  "JUMPDEST ", 
  "PUSH1 0x04 ", 
  "DUP2 ", 
  "SWAP1 ", 
  "SSTORE ", 
  "POP ", 
  "DUP4 ", 
  "PUSH1 0x03 ", 
  "SLOAD ", 
  "PUSH1 0x04 ", 
  "SLOAD ", 
  "PUSH32 0xcc8d22e807ea92fa44cbc984df35dfbb8351ddf6302b105e5e3cef56dbe45712 ", 
  "PUSH1 0x40 ", 
  "MLOAD ", 
  "PUSH1 0x40 ", 
  "MLOAD ", 
  "DUP1 ", 
  "SWAP2 ", 
  "SUB ", 
  "SWAP1 ", 
  "LOG4 ", 
  "POP ", 
  "POP ", 
  "POP ", 
  "POP ", 
  "JUMP ", 
  "JUMPDEST ", 
  "STOP "
 ], 
 "overflow": false, 
 "money_concurrency": "\nFlow 1:\n./0x009ef15c147ff4c0eb373e1abd2f4d184e5cb916_ext.sol:CampaignContract:182:3\nmsg.sender.transfer(amount)\n^\nFlow 2:", 
 "truncation": false
},"SafeMath-3":{
 "execution_paths": "1", 
 "callstack": false, 
 "reentrancy": false, 
 "modulo": false, 
 "division": false, 
 "execution_time": "0.00842905044556", 
 "signedness": false, 
 "evm_code_coverage": "100.0", 
 "underflow": false, 
 "time_dependency": false, 
 "assertion_failure": false, 
 "timeout": false, 
 "dead_code": [], 
 "overflow": false, 
 "money_concurrency": false, 
 "truncation": false
},"CampaignContract-4":{
 "execution_paths": "108", 
 "callstack": false, 
 "reentrancy": false, 
 "modulo": false, 
 "division": false, 
 "execution_time": "9.44767594337", 
 "signedness": false, 
 "evm_code_coverage": "98.8", 
 "underflow": false, 
 "time_dependency": false, 
 "assertion_failure": false, 
 "timeout": false, 
 "dead_code": [
  "JUMPDEST ", 
  "PUSH1 0x03 ", 
  "DUP2 ", 
  "SWAP1 ", 
  "SSTORE ", 
  "POP ", 
  "PUSH2 0x0b38 ", 
  "JUMPDEST ", 
  "DUP4 ", 
  "DUP4 ", 
  "PUSH2 0x2123 ", 
  "SWAP1 ", 
  "SWAP2 ", 
  "SWAP1 ", 
  "PUSH4 0xffffffff ", 
  "STOP ", 
  "STOP ", 
  "AND ", 
  "JUMP ", 
  "JUMPDEST ", 
  "PUSH1 0x04 ", 
  "DUP2 ", 
  "SWAP1 ", 
  "SSTORE ", 
  "POP ", 
  "DUP4 ", 
  "PUSH1 0x03 ", 
  "SLOAD ", 
  "PUSH1 0x04 ", 
  "SLOAD ", 
  "PUSH32 0xcc8d22e807ea92fa44cbc984df35dfbb8351ddf6302b105e5e3cef56dbe45712 ", 
  "PUSH1 0x40 ", 
  "MLOAD ", 
  "PUSH1 0x40 ", 
  "MLOAD ", 
  "DUP1 ", 
  "SWAP2 ", 
  "SUB ", 
  "SWAP1 ", 
  "LOG4 ", 
  "POP ", 
  "POP ", 
  "POP ", 
  "POP ", 
  "JUMP ", 
  "JUMPDEST ", 
  "STOP "
 ], 
 "overflow": false, 
 "money_concurrency": "\nFlow 1:\n./0x009ef15c147ff4c0eb373e1abd2f4d184e5cb916_ext.sol:CampaignContract:182:3\nmsg.sender.transfer(amount)\n^\nFlow 2:", 
 "truncation": false
},"SafeMath-4":{
 "execution_paths": "1", 
 "callstack": false, 
 "reentrancy": false, 
 "modulo": false, 
 "division": false, 
 "execution_time": "0.0116260051727", 
 "signedness": false, 
 "evm_code_coverage": "100.0", 
 "underflow": false, 
 "time_dependency": false, 
 "assertion_failure": false, 
 "timeout": false, 
 "dead_code": [], 
 "overflow": false, 
 "money_concurrency": false, 
 "truncation": false
},"CampaignContract-5":{
 "execution_paths": "108", 
 "callstack": false, 
 "reentrancy": false, 
 "modulo": false, 
 "division": false, 
 "execution_time": "10.203455925", 
 "signedness": false, 
 "evm_code_coverage": "98.8", 
 "underflow": false, 
 "time_dependency": false, 
 "assertion_failure": false, 
 "timeout": false, 
 "dead_code": [
  "JUMPDEST ", 
  "PUSH1 0x03 ", 
  "DUP2 ", 
  "SWAP1 ", 
  "SSTORE ", 
  "POP ", 
  "PUSH2 0x0b38 ", 
  "JUMPDEST ", 
  "DUP4 ", 
  "DUP4 ", 
  "PUSH2 0x2123 ", 
  "SWAP1 ", 
  "SWAP2 ", 
  "SWAP1 ", 
  "PUSH4 0xffffffff ", 
  "STOP ", 
  "STOP ", 
  "AND ", 
  "JUMP ", 
  "JUMPDEST ", 
  "PUSH1 0x04 ", 
  "DUP2 ", 
  "SWAP1 ", 
  "SSTORE ", 
  "POP ", 
  "DUP4 ", 
  "PUSH1 0x03 ", 
  "SLOAD ", 
  "PUSH1 0x04 ", 
  "SLOAD ", 
  "PUSH32 0xcc8d22e807ea92fa44cbc984df35dfbb8351ddf6302b105e5e3cef56dbe45712 ", 
  "PUSH1 0x40 ", 
  "MLOAD ", 
  "PUSH1 0x40 ", 
  "MLOAD ", 
  "DUP1 ", 
  "SWAP2 ", 
  "SUB ", 
  "SWAP1 ", 
  "LOG4 ", 
  "POP ", 
  "POP ", 
  "POP ", 
  "POP ", 
  "JUMP ", 
  "JUMPDEST ", 
  "STOP "
 ], 
 "overflow": false, 
 "money_concurrency": "\nFlow 1:\n./0x009ef15c147ff4c0eb373e1abd2f4d184e5cb916_ext.sol:CampaignContract:182:3\nmsg.sender.transfer(amount)\n^\nFlow 2:", 
 "truncation": false
},"SafeMath-5":{
 "execution_paths": "1", 
 "callstack": false, 
 "reentrancy": false, 
 "modulo": false, 
 "division": false, 
 "execution_time": "0.0114190578461", 
 "signedness": false, 
 "evm_code_coverage": "100.0", 
 "underflow": false, 
 "time_dependency": false, 
 "assertion_failure": false, 
 "timeout": false, 
 "dead_code": [], 
 "overflow": false, 
 "money_concurrency": false, 
 "truncation": false
},"CampaignContract-6":{
 "execution_paths": "108", 
 "callstack": false, 
 "reentrancy": false, 
 "modulo": false, 
 "division": false, 
 "execution_time": "9.11347317696", 
 "signedness": false, 
 "evm_code_coverage": "98.8", 
 "underflow": false, 
 "time_dependency": false, 
 "assertion_failure": false, 
 "timeout": false, 
 "dead_code": [
  "JUMPDEST ", 
  "PUSH1 0x03 ", 
  "DUP2 ", 
  "SWAP1 ", 
  "SSTORE ", 
  "POP ", 
  "PUSH2 0x0b38 ", 
  "JUMPDEST ", 
  "DUP4 ", 
  "DUP4 ", 
  "PUSH2 0x2123 ", 
  "SWAP1 ", 
  "SWAP2 ", 
  "SWAP1 ", 
  "PUSH4 0xffffffff ", 
  "STOP ", 
  "STOP ", 
  "AND ", 
  "JUMP ", 
  "JUMPDEST ", 
  "PUSH1 0x04 ", 
  "DUP2 ", 
  "SWAP1 ", 
  "SSTORE ", 
  "POP ", 
  "DUP4 ", 
  "PUSH1 0x03 ", 
  "SLOAD ", 
  "PUSH1 0x04 ", 
  "SLOAD ", 
  "PUSH32 0xcc8d22e807ea92fa44cbc984df35dfbb8351ddf6302b105e5e3cef56dbe45712 ", 
  "PUSH1 0x40 ", 
  "MLOAD ", 
  "PUSH1 0x40 ", 
  "MLOAD ", 
  "DUP1 ", 
  "SWAP2 ", 
  "SUB ", 
  "SWAP1 ", 
  "LOG4 ", 
  "POP ", 
  "POP ", 
  "POP ", 
  "POP ", 
  "JUMP ", 
  "JUMPDEST ", 
  "STOP "
 ], 
 "overflow": false, 
 "money_concurrency": "\nFlow 1:\n./0x009ef15c147ff4c0eb373e1abd2f4d184e5cb916_ext.sol:CampaignContract:182:3\nmsg.sender.transfer(amount)\n^\nFlow 2:", 
 "truncation": false
},"SafeMath-6":{
 "execution_paths": "1", 
 "callstack": false, 
 "reentrancy": false, 
 "modulo": false, 
 "division": false, 
 "execution_time": "0.0115880966187", 
 "signedness": false, 
 "evm_code_coverage": "100.0", 
 "underflow": false, 
 "time_dependency": false, 
 "assertion_failure": false, 
 "timeout": false, 
 "dead_code": [], 
 "overflow": false, 
 "money_concurrency": false, 
 "truncation": false
}}